Workbook

Sheet Mon
A1: Republic Hotel - Daily Takings
A2: MONDAY
K3: DATE: | L3: 46055 | N3: SUNDRIES | Q3: FOOD
A4: BISTRO | B4: READING | C4: FOOD | D4: TYRO FEE | E4: TIPS | F4: EXPECTED | G4: EFTPOS | H4: AMEX/DINER | I4: ME&U | J4: CASH | K4: VAR (+ / -) | L4: ACCOUNT | Q4: =A4 -> BISTRO | R4: =C8 -> 0
F5: =B5-(D5+L5) -> 0 | K5: =SUM(I5+J5+H5+G5)-F5 -> 0 | Q5: =A11 -> SPORTS BAR | R5: =C15 -> 0
F6: =B6-(D6+L6) -> 0 | K6: =SUM(I6+J6+H6+G6)-F6 -> 0 | Q6: BALCONY | R6: =C22+C28 -> 0
F7: =B7-(D7+L7) -> 0 | K7: =SUM(I7+J7+H7+G7)-F7 -> 0 | N7: TOTAL | O7: =O4+O5+O6 -> 0 | Q7: PUBLIC 1 / 2 | R7: =+C36+C42 -> 0
A8: TOTALS | B8: =SUM(B5:B7) -> 0 | C8: =SUM(C5:C7) -> 0 | D8: =SUM(D5:D7) -> 0 | E8: =SUM(E5:E7) -> 0 | F8: =SUM(F5:F7) -> 0 | G8: =SUM(G5:G7) -> 0 | H8: =SUM(H5:H7) -> 0 | I8: =SUM(I5:I7) -> 0 | J8: =SUM(J5:J7) -> 0 | K8: =SUM(I8+J8+H8+G8)-F8 -> 0 | L8: =SUM(L5:L7) -> 0 | Q8: BISTRO TILL | R8: =C57 -> 0
G9: BISTRO TOTAL | J9: =SUM(I8+J8+H8+G8)-C8-E8 -> 0 | Q9: TOTAL | R9: =SUM(R4:R8) -> 0
N10: TAB
A11: SPORTS BAR | B11: READING | C11: FOOD | D11: TYRO FEE | E11: TIPS | F11: EXPECTED | G11: EFTPOS | H11: AMEX/DINER | I11: ME&U | J11: CASH | K11: VAR (+ / -) | L11: ACCOUNT | N11: SALES | Q11: POKIES
F12: =B12-(D12+L12) -> 0 | K12: =SUM(I12+J12+H12+G12)-F12 -> 0 | N12: TERMINAL | O12: 0 | Q12: CASH BOX
F13: =B13-(D13+L13) -> 0 | K13: =SUM(I13+J13+H13+G13)-F13 -> 0 | N13: EBET 1 | Q13: TICKET IN
F14: =B14-(D14+L14) -> 0 | K14: =SUM(I14+J14+H14+G14)-F14 -> 0 | N14: EBET 2 | Q14: CASH IN | R14: =R12-R13 -> 0
A15: TOTALS | B15: =SUM(B12:B14) -> 0 | C15: =SUM(C12:C14) -> 0 | D15: =SUM(D12:D14) -> 0 | E15: =SUM(E12:E14) -> 0 | F15: =SUM(F12:F14) -> 0 | G15: =SUM(G12:G14) -> 0 | H15: =SUM(H12:H14) -> 0 | I15: =SUM(I12:I14) -> 0 | ... L15: =SUM(L12:L14) -> 0 | N15: TOTAL | O15: =SUM(O12:O14) -> 0 | Q15: MONEY OUT
G16: SPORTS BAR TOTAL | J16: =SUM(I15+J15+H15+G15)-C15-E15 -> 0 | N16: LIABILITY | Q16: LINK AUTO
N17: TERMINAL | Q17: LINK MAN
A18: PUBLIC 1 | B18: READING | C18: FOOD | D18: TYRO FEE | E18: TIPS | F18: EXPECTED | G18: EFTPOS | H18: AMEX/DINER | I18: ME&U | J18: CASH | K18: VAR (+ / -) | L18: ACCOUNT | N18: EBET 1 | Q18: C/CREDITS
F19: =B19-(D19+L19) -> 0 | K19: =SUM(I19+J19+H19+G19)-F19 -> 0 | N19: EBET 2 | Q19: NET | R19: =R12-R15-R17-R18 -> 0
F20: =B20-(D20+L20) -> 0 | K20: =SUM(I20+J20+H20+G20)-F20 -> 0 | N20: TOTAL | O20: =SUM(O17:O19) -> 0 | Q20: TURNOVER
F21: =B21-(D21+L21) -> 0 | K21: =SUM(I21+J21+H21+G21)-F21 -> 0
A22: TOTALS | B22: =SUM(B19:B21) -> 0 | C22: =SUM(C19:C21) -> 0 | D22: =SUM(D19:D21) -> 0 | E22: =SUM(E19:E21) -> 0 | F22: =SUM(F19:F21) -> 0 | G22: =SUM(G19:G21) -> 0 | H22: =SUM(H19:H21) -> 0 | I22: =SUM(I19:I21) -> 0 | ... L22: =SUM(L19:L21) -> 0 | N22: EFTPOS
N23: =A11 -> SPORTS BAR | O23: =G15 -> 0 | Q23: TOTALS
A24: PUBLIC 2/GAMING | B24: READING | C24: FOOD | D24: TYRO FEE | E24: TIPS | F24: EXPECTED | G24: EFTPOS | H24: AMEX/DINER | I24: ME&U | J24: CASH | K24: VAR (+ / -) | L24: ACCOUNT | N24: =A4 -> BISTRO | O24: =G8 -> 0 | Q24: RECEIPTS | R24: =SUM(J29,J51,O7,J43,J16,J9,R19,J58,R9) -> 0
F25: =B25-(D25+L25) -> 0 | K25: =SUM(I25+J25+H25+G25)-F25 -> 0 | N25: B/SHOP | O25: =G50 -> 0 | Q25: GST | R25: =ROUND(+R24/11,2) -> 0
F26: =B26-(D26+L26) -> 0 | K26: =SUM(I26+J26+H26+G26)-F26 -> 0 | N26: PUBLIC 1 | O26: =G22 -> 0 | Q26: ATM | R26: =R39 -> 0
F27: =B27-(D27+L27) -> 0 | K27: =SUM(I27+J27+H27+G27)-F27 -> 0 | N27: PUBLIC 2 | O27: =G28 -> 0 | Q27: ME&U | R27: =I57+I42+I36+I28+I22+I15+I8 -> 0
A28: TOTALS | B28: =SUM(B25:B27) -> 0 | C28: =SUM(C25:C27) -> 0 | D28: =SUM(D25:D27) -> 0 | E28: =SUM(E25:E27) -> 0 | F28: =SUM(F25:F27) -> 0 | G28: =SUM(G25:G27) -> 0 | H28: =SUM(H25:H27) -> 0 | I28: =SUM(I25:I27) -> 0 | ... L28: =SUM(L25:L27) -> 0 | N28: ROOF TOP 1 | O28: =G36 -> 0 | Q28: EFTPOS | R28: =O31 -> 0
G29: PUBLIC BAR TOTAL | J29: =SUM(G22+H22+I22+J22)+(I28+J28+H28+G28)-C28-E28-C22-E22 -> 0 | N29: ROOF TOP 2 | O29: =G42 -> 0 | Q29: BANKING | R29: =R24-(R28+R26+R27) -> 0
N30: BISTRO | O30: =G57 -> 0
A31: TAYLORS BAR | N31: TOTAL | O31: =SUM(O23:O30) -> 0 | Q31: TAKING TIN | R31: =J8+J15+J22+J28+J36+J42+J50+J57 -> 0
A32: ROOF TOP 1 | B32: READING | C32: FOOD | D32: TYRO FEE | E32: TIPS | F32: EXPECTED | G32: EFTPOS | H32: AMEX/DINER | I32: ME&U | J32: CASH | K32: VAR (+ / -) | L32: ACCOUNT
F33: =B33-(D33+L33) -> 0 | K33: =SUM(I33+J33+H33+G33)-F33 -> 0 | Q33: TAB (ATM)
F34: =B34-(D34+L34) -> 0 | K34: =SUM(I34+J34+H34+G34)-F34 -> 0
F35: =B35-(D35+L35) -> 0 | K35: =SUM(I35+J35+H35+G35)-F35 -> 0
A36: TOTALS | B36: =SUM(B33:B35) -> 0 | C36: =SUM(C33:C35) -> 0 | D36: =SUM(D33:D35) -> 0 | E36: =SUM(E33:E35) -> 0 | F36: =SUM(F33:F35) -> 0 | G36: =SUM(G33:G35) -> 0 | H36: =SUM(H33:H35) -> 0 | I36: =SUM(I33:I35) -> 0 | ... L36: =SUM(L33:L35) -> 0 | Q36: ATM REFILL
Q37: ATM 1
A38: ROOF TOP 2 | B38: READING | C38: FOOD | D38: TYRO FEE | E38: TIPS | F38: EXPECTED | G38: EFTPOS | H38: AMEX/DINER | I38: ME&U | J38: CASH | K38: VAR (+ / -) | L38: ACCOUNT | Q38: ATM 2
F39: =B39-(D39+L39) -> 0 | K39: =SUM(I39+J39+H39+G39)-F39 -> 0 | Q39: TOTAL | R39: =SUM(R37:R38) -> 0
F40: =B40-(D40+L40) -> 0 | K40: =SUM(I40+J40+H40+G40)-F40 -> 0
F41: =B41-(D41+L41) -> 0 | K41: =SUM(I41+J41+H41+G41)-F41 -> 0
A42: TOTALS | B42: =SUM(B39:B41) -> 0 | C42: =SUM(C39:C41) -> 0 | D42: =SUM(D39:D41) -> 0 | E42: =SUM(E39:E41) -> 0 | F42: =SUM(F39:F41) -> 0 | G42: =SUM(G39:G41) -> 0 | H42: =SUM(H39:H41) -> 0 | I42: =SUM(I39:I41) -> 0 | ... L42: =SUM(L39:L41) -> 0
G43: ROOF TOP TOTAL | J43: =SUM(G36+H36+I36+J36)+(I42+J42+H42+G42)-C36-C42-E36-E42 -> 0
A45: BOTTLE SHOP | B45: READING | C45: TYRO FEE | D45: TYRO FEE | E45: TIPS | F45: EXPECTED | G45: EFTPOS | H45: AMEX/DINER | I45: ME&U | J45: CASH | K45: VAR (+ / -) | L45: ACCOUNT
F46: =B46-(D46+L46) -> 0 | K46: =SUM(I46+J46+H46+G46)-F46 -> 0
F47: =B47-(D47+L47) -> 0 | K47: =SUM(I47+J47+H47+G47)-F47 -> 0
F48: =B48-(D48+L48) -> 0 | K48: =SUM(I48+J48+H48+G48)-F48 -> 0
F49: =B49-(D49+L49) -> 0 | K49: =SUM(I49+J49+H49+G49)-F49 -> 0
A50: TOTALS | B50: =SUM(B46:B49) -> 0 | C50: =SUM(C46:C49) -> 0 | D50: =SUM(D46:D49) -> 0 | E50: =SUM(E46:E49) -> 0 | F50: =SUM(F46:F49) -> 0 | G50: =SUM(G46:G49) -> 0 | H50: =SUM(H46:H49) -> 0 | I50: =SUM(I46:I49) -> 0 | ... L50: =SUM(L46:L49) -> 0
G51: BOTTLE SHOP TOTAL | J51: =SUM(I50+J50+H50+G50)-E50 -> 0
A53: BISTRO TILL | B53: READING | C53: FOOD | D53: TYRO FEE | E53: TIPS | F53: EXPECTED | G53: EFTPOS | H53: AMEX/DINER | I53: ME&U | J53: CASH | K53: VAR (+ / -) | L53: ACCOUNT
F54: =B54-(D54+L54) -> 0 | K54: =SUM(I54+J54+H54+G54)-F54 -> 0
F55: =B55-(D55+L55) -> 0 | K55: =SUM(I55+J55+H55+G55)-F55 -> 0
F56: =B56-(D56+L56) -> 0 | K56: =SUM(I56+J56+H56+G56)-F56 -> 0
A57: TOTALS | B57: =SUM(B54:B56) -> 0 | C57: =SUM(C54:C56) -> 0 | D57: =SUM(D54:D56) -> 0 | E57: =SUM(E54:E56) -> 0 | F57: =SUM(F54:F56) -> 0 | G57: =SUM(G54:G56) -> 0 | H57: =SUM(H54:H56) -> 0 | I57: =SUM(I54:I56) -> 0 | ... L57: =SUM(L54:L56) -> 0
G58: BISTRO TILL TOTAL | J58: =SUM(I57+J57+H57+G57)-C57-E57 -> 0

Sheet Mon diary
A1: Republic Hotel
A2: =Mon!L3 -> 46055
A3: Weather
A5: Summary | B5: Monday | F5: Bars | G5: =SUM(G6:G9) -> 0
A6: Gaming Turnover | B6: =Takings!B24 -> 0 | F6: Public | G6: =Takings!C5 -> 0
A7: Gaming Gross | B7: =Takings!C24 -> 0 | F7: Bistro | G7: =Takings!D5 -> 0
A8: Gaming Net | B8: =Takings!I5 -> 0 | F8: Sports | G8: =Takings!E5 -> 0
A9: Dragon Link (50K) | F9: Taylors | G9: =Takings!F5 -> 0
A10: Dragon Train (20K)
A11: Fortune Hearts (25K)
A12: Dragon Rush (90K)
A13: Dragon Link (90K)
A14: Thunder Empire (50K) | F14: Bistro & Food Service
A15: Power Panther (12K) | F15: Day Covers | G15: =B45 -> 0 | H15: Night Covers | I15: =D45 -> 0
A16: Bars | B16: =Takings!B46 -> 0 | F16: LUNCH Service Feedback
A17: Food | B17: =Takings!B49 -> 0
A18: Retail | B18: =Takings!H5 -> 0 | F18: Dinner Service Feedback
A19: TAB | B19: =Takings!L37 -> 0
F20: Public Bar
B21: DAY | C21: MID | D21: CLOSE | F21: Food | G21: =Mon!C22+Mon!C28 -> 0 | H21: Bev | I21: =Mon!J29 -> 0
A22: Managers Name | F22: Day
B23: GAMING
A24: Day turnover up to 6pm | B24: =G75 -> 0 | C24: Staff | F24: Evening
A25: How was the days trade
A26: Who were your big punters | F26: Late Night
A27: Large payouts/links & to whom
A28: Night turnover after 6pm | B28: =B6-B24 -> 0 | C28: Staff | F28: Bistro
A29: How was the night trade | F29: Food | G29: =Mon!C8 -> 0 | H29: Bev | I29: =Mon!J9 -> 0
A30: Who were your big punters | F30: Day
A31: Large payouts/links & to whom
B32: LINKS IF WON | F32: Evening
A33: What Link did they win
A34: How much was the Link | F34: Late Night
A35: What machine number
A36: How much were they betting | F36: Sports Bar
A37: Are they a regular | F37: Food | G37: =Mon!C15 -> 0 | H37: Bev | I37: =Mon!J16 -> 0
B38: AUSTRAC REPORTING | F38: Day
A39: Any Suspicious Customers
A40: Cash In to Turnover Ratio | B40: =Takings!B24/Takings!E24 -> #DIV/0! | F40: Evening
A41: Checked by
B42: TAB | F42: Late Night
A43: How was day trade
A44: How was night trade | F44: Taylors Rooftop
A45: Feedback/Issues | F45: Food | G45: =Mon!C36+Mon!C42 -> 0 | H45: Bev | I45: =Mon!J43 -> 0
F46: Day
B47: RETAIL
A48: How was day trade | F48: Evening
A49: How was night trade
B50: WHAT'S ON | F50: Late Night
A51: Event name(s)
A52: How many people | C52: Jackpot $
A53: Feedback
B54: FUNCTIONS | F54: Food Service
A55: Type of function | F55: Time | G55: Food served | J55: Portions Taken
A56: How many people
A57: Feedback
B58: CASHING UP
A59: Enter Safe Variance Amount
A60: Explanation if (+/- $20)
B61: SECURITY
A62: Any issues
A64: Who & how were guards
B65: COMPLIANCE | F65: GAMING | H65: HOURLY | I65: PATRON | J65: ROOM
A66: STAR COMPLIANCE FILLED IN (Y/N) | F66: ROOM | G66: TURNOVER | H66: TURNOVER | I66: NUMBERS | J66: TEMP
A67: CCTV CHECK (Y/N) | F67: 10am | J67: 23
A68: Police visits or incidents | F68: 11am | H68: =G68-G67 -> 0 | J68: 23
A69: OLGR visits or incidents | F69: 12pm | H69: =G69-G68 -> 0 | J69: 23
B70: OH&S | F70: 1pm | H70: =G70-G69 -> 0 | J70: 23
A71: Any injuries? | F71: 2pm | H71: =G71-G70 -> 0 | J71: 23
A72: Treatment provided (Sent to Dr?) | F72: 3pm | H72: =G72-G71 -> 0 | J72: 23
F73: 4pm | H73: =G73-G72 -> 0 | J73: 23
F74: 5pm | H74: =G74-G73 -> 0 | J74: 23
F75: 6pm | H75: =G75-G74 -> 0 | J75: 23
F76: 7pm | H76: =G76-G75 -> 0 | J76: 23
F77: 8pm | H77: =G77-G76 -> 0 | J77: 23
F78: 9pm | H78: =G78-G77 -> 0 | J78: 23
F79: 10pm | H79: =G79-G78 -> 0 | J79: 23
F80: 11pm | H80: =G80-G79 -> 0 | J80: 23
F81: 12am | H81: =G81-G80 -> 0 | J81: 23
F82: 1am | H82: =G82-G81 -> 0 | J82: 23
F83: 2am | H83: =G83-G82 -> 0 | J83: 23
F84: 3am | H84: =G84-G83 -> 0 | J84: 23
F85: 4am | H85: =G85-G84 -> 0 | J85: 23

Sheet Tue
A1: Republic Hotel - Daily Takings
A2: TUESDAY
K3: DATE: | L3: =Mon!L3+1 -> 46056 | N3: SUNDRIES | Q3: FOOD
A4: BISTRO | B4: READING | C4: FOOD | D4: TYRO FEE | E4: TIPS | F4: EXPECTED | G4: EFTPOS | H4: AMEX/DINER | I4: ME&U | J4: CASH | K4: VAR (+ / -) | L4: ACCOUNT | Q4: =A4 -> BISTRO | R4: =C8 -> 0
F5: =B5-(D5+L5) -> 0 | K5: =SUM(I5+J5+H5+G5)-F5 -> 0 | Q5: =A11 -> SPORTS BAR | R5: =C15 -> 0
F6: =B6-(D6+L6) -> 0 | K6: =SUM(I6+J6+H6+G6)-F6 -> 0 | Q6: BALCONY | R6: =C22+C28 -> 0
F7: =B7-(D7+L7) -> 0 | K7: =SUM(I7+J7+H7+G7)-F7 -> 0 | N7: TOTAL | O7: =O4+O5+O6 -> 0 | Q7: PUBLIC 1 / 2 | R7: =+C36+C42 -> 0
A8: TOTALS | B8: =SUM(B5:B7) -> 0 | C8: =SUM(C5:C7) -> 0 | D8: =SUM(D5:D7) -> 0 | E8: =SUM(E5:E7) -> 0 | F8: =SUM(F5:F7) -> 0 | G8: =SUM(G5:G7) -> 0 | H8: =SUM(H5:H7) -> 0 | I8: =SUM(I5:I7) -> 0 | J8: =SUM(J5:J7) -> 0 | K8: =SUM(I8+J8+H8+G8)-F8 -> 0 | L8: =SUM(L5:L7) -> 0 | Q8: BISTRO TILL | R8: =C57 -> 0
G9: BISTRO TOTAL | J9: =SUM(I8+J8+H8+G8)-C8-E8 -> 0 | Q9: TOTAL | R9: =SUM(R4:R8) -> 0
N10: TAB
A11: SPORTS BAR | B11: READING | C11: FOOD | D11: TYRO FEE | E11: TIPS | F11: EXPECTED | G11: EFTPOS | H11: AMEX/DINER | I11: ME&U | J11: CASH | K11: VAR (+ / -) | L11: ACCOUNT | N11: SALES | Q11: POKIES
F12: =B12-(D12+L12) -> 0 | K12: =SUM(I12+J12+H12+G12)-F12 -> 0 | N12: TERMINAL | Q12: CASH BOX
F13: =B13-(D13+L13) -> 0 | K13: =SUM(I13+J13+H13+G13)-F13 -> 0 | N13: EBET 1 | Q13: TICKET IN
F14: =B14-(D14+L14) -> 0 | K14: =SUM(I14+J14+H14+G14)-F14 -> 0 | N14: EBET 2 | Q14: CASH IN | R14: =R12-R13 -> 0
A15: TOTALS | B15: =SUM(B12:B14) -> 0 | C15: =SUM(C12:C14) -> 0 | D15: =SUM(D12:D14) -> 0 | E15: =SUM(E12:E14) -> 0 | F15: =SUM(F12:F14) -> 0 | G15: =SUM(G12:G14) -> 0 | H15: =SUM(H12:H14) -> 0 | I15: =SUM(I12:I14) -> 0 | ... L15: =SUM(L12:L14) -> 0 | N15: TOTAL | O15: =SUM(O12:O14) -> 0 | Q15: MONEY OUT
G16: SPORTS BAR TOTAL | J16: =SUM(I15+J15+H15+G15)-C15-E15 -> 0 | N16: LIABILITY | Q16: LINK AUTO
N17: TERMINAL | Q17: LINK MAN
A18: PUBLIC 1 | B18: READING | C18: FOOD | D18: TYRO FEE | E18: TIPS | F18: EXPECTED | G18: EFTPOS | H18: AMEX/DINER | I18: ME&U | J18: CASH | K18: VAR (+ / -) | L18: ACCOUNT | N18: EBET 1 | Q18: C/CREDITS
F19: =B19-(D19+L19) -> 0 | K19: =SUM(I19+J19+H19+G19)-F19 -> 0 | N19: EBET 2 | Q19: NET | R19: =R12-R15-R17-R18 -> 0
F20: =B20-(D20+L20) -> 0 | K20: =SUM(I20+J20+H20+G20)-F20 -> 0 | N20: TOTAL | O20: =SUM(O17:O19) -> 0 | Q20: TURNOVER
F21: =B21-(D21+L21) -> 0 | K21: =SUM(I21+J21+H21+G21)-F21 -> 0
A22: TOTALS | B22: =SUM(B19:B21) -> 0 | C22: =SUM(C19:C21) -> 0 | D22: =SUM(D19:D21) -> 0 | E22: =SUM(E19:E21) -> 0 | F22: =SUM(F19:F21) -> 0 | G22: =SUM(G19:G21) -> 0 | H22: =SUM(H19:H21) -> 0 | I22: =SUM(I19:I21) -> 0 | ... L22: =SUM(L19:L21) -> 0 | N22: EFTPOS
N23: =A11 -> SPORTS BAR | O23: =G15 -> 0 | Q23: TOTALS
A24: PUBLIC 2/GAMING | B24: READING | C24: FOOD | D24: TYRO FEE | E24: TIPS | F24: EXPECTED | G24: EFTPOS | H24: AMEX/DINER | I24: ME&U | J24: CASH | K24: VAR (+ / -) | L24: ACCOUNT | N24: =A4 -> BISTRO | O24: =G8 -> 0 | Q24: RECEIPTS | R24: =SUM(J29,J51,O7,J43,J16,J9,R19,J58,R9) -> 0
F25: =B25-(D25+L25) -> 0 | K25: =SUM(I25+J25+H25+G25)-F25 -> 0 | N25: B/SHOP | O25: =G50 -> 0 | Q25: GST | R25: =ROUND(+R24/11,2) -> 0
F26: =B26-(D26+L26) -> 0 | K26: =SUM(I26+J26+H26+G26)-F26 -> 0 | N26: PUBLIC 1 | O26: =G22 -> 0 | Q26: ATM | R26: =R39 -> 0
F27: =B27-(D27+L27) -> 0 | K27: =SUM(I27+J27+H27+G27)-F27 -> 0 | N27: PUBLIC 2 | O27: =G28 -> 0 | Q27: ME&U | R27: =I57+I42+I36+I28+I22+I15+I8 -> 0
A28: TOTALS | B28: =SUM(B25:B27) -> 0 | C28: =SUM(C25:C27) -> 0 | D28: =SUM(D25:D27) -> 0 | E28: =SUM(E25:E27) -> 0 | F28: =SUM(F25:F27) -> 0 | G28: =SUM(G25:G27) -> 0 | H28: =SUM(H25:H27) -> 0 | I28: =SUM(I25:I27) -> 0 | ... L28: =SUM(L25:L27) -> 0 | N28: ROOF TOP 1 | O28: =G36 -> 0 | Q28: EFTPOS | R28: =O31 -> 0
G29: PUBLIC BAR TOTAL | J29: =SUM(G22+H22+I22+J22)+(I28+J28+H28+G28)-C28-E28-C22-E22 -> 0 | N29: ROOF TOP 2 | O29: =G42 -> 0 | Q29: BANKING | R29: =R24-(R28+R26+R27) -> 0
N30: BISTRO | O30: =G57 -> 0
A31: TAYLORS BAR | N31: TOTAL | O31: =SUM(O23:O30) -> 0 | Q31: TAKING TIN | R31: =J8+J15+J22+J28+J36+J42+J50+J57 -> 0
A32: ROOF TOP 1 | B32: READING | C32: FOOD | D32: TYRO FEE | E32: TIPS | F32: EXPECTED | G32: EFTPOS | H32: AMEX/DINER | I32: ME&U | J32: CASH | K32: VAR (+ / -) | L32: ACCOUNT
F33: =B33-(D33+L33) -> 0 | K33: =SUM(I33+J33+H33+G33)-F33 -> 0 | Q33: TAB (ATM)
F34: =B34-(D34+L34) -> 0 | K34: =SUM(I34+J34+H34+G34)-F34 -> 0
F35: =B35-(D35+L35) -> 0 | K35: =SUM(I35+J35+H35+G35)-F35 -> 0
A36: TOTALS | B36: =SUM(B33:B35) -> 0 | C36: =SUM(C33:C35) -> 0 | D36: =SUM(D33:D35) -> 0 | E36: =SUM(E33:E35) -> 0 | F36: =SUM(F33:F35) -> 0 | G36: =SUM(G33:G35) -> 0 | H36: =SUM(H33:H35) -> 0 | I36: =SUM(I33:I35) -> 0 | ... L36: =SUM(L33:L35) -> 0 | Q36: ATM REFILL
Q37: ATM 1
A38: ROOF TOP 2 | B38: READING | C38: FOOD | D38: TYRO FEE | E38: TIPS | F38: EXPECTED | G38: EFTPOS | H38: AMEX/DINER | I38: ME&U | J38: CASH | K38: VAR (+ / -) | L38: ACCOUNT | Q38: ATM 2
F39: =B39-(D39+L39) -> 0 | K39: =SUM(I39+J39+H39+G39)-F39 -> 0 | Q39: TOTAL | R39: =SUM(R37:R38) -> 0
F40: =B40-(D40+L40) -> 0 | K40: =SUM(I40+J40+H40+G40)-F40 -> 0
F41: =B41-(D41+L41) -> 0 | K41: =SUM(I41+J41+H41+G41)-F41 -> 0
A42: TOTALS | B42: =SUM(B39:B41) -> 0 | C42: =SUM(C39:C41) -> 0 | D42: =SUM(D39:D41) -> 0 | E42: =SUM(E39:E41) -> 0 | F42: =SUM(F39:F41) -> 0 | G42: =SUM(G39:G41) -> 0 | H42: =SUM(H39:H41) -> 0 | I42: =SUM(I39:I41) -> 0 | ... L42: =SUM(L39:L41) -> 0
G43: ROOF TOP TOTAL | J43: =SUM(G36+H36+I36+J36)+(I42+J42+H42+G42)-C36-C42-E36-E42 -> 0
A45: BOTTLE SHOP | B45: READING | C45: TYRO FEE | D45: TYRO FEE | E45: TIPS | F45: EXPECTED | G45: EFTPOS | H45: AMEX/DINER | I45: ME&U | J45: CASH | K45: VAR (+ / -) | L45: ACCOUNT
F46: =B46-(D46+L46) -> 0 | K46: =SUM(I46+J46+H46+G46)-F46 -> 0
F47: =B47-(D47+L47) -> 0 | K47: =SUM(I47+J47+H47+G47)-F47 -> 0
F48: =B48-(D48+L48) -> 0 | K48: =SUM(I48+J48+H48+G48)-F48 -> 0
F49: =B49-(D49+L49) -> 0 | K49: =SUM(I49+J49+H49+G49)-F49 -> 0
A50: TOTALS | B50: =SUM(B46:B49) -> 0 | C50: =SUM(C46:C49) -> 0 | D50: =SUM(D46:D49) -> 0 | E50: =SUM(E46:E49) -> 0 | F50: =SUM(F46:F49) -> 0 | G50: =SUM(G46:G49) -> 0 | H50: =SUM(H46:H49) -> 0 | I50: =SUM(I46:I49) -> 0 | ... L50: =SUM(L46:L49) -> 0
G51: BOTTLE SHOP TOTAL | J51: =SUM(I50+J50+H50+G50)-E50 -> 0
A53: BISTRO TILL | B53: READING | C53: FOOD | D53: TYRO FEE | E53: TIPS | F53: EXPECTED | G53: EFTPOS | H53: AMEX/DINER | I53: ME&U | J53: CASH | K53: VAR (+ / -) | L53: ACCOUNT
F54: =B54-(D54+L54) -> 0 | K54: =SUM(I54+J54+H54+G54)-F54 -> 0
F55: =B55-(D55+L55) -> 0 | K55: =SUM(I55+J55+H55+G55)-F55 -> 0
F56: =B56-(D56+L56) -> 0 | K56: =SUM(I56+J56+H56+G56)-F56 -> 0
A57: TOTALS | B57: =SUM(B54:B56) -> 0 | C57: =SUM(C54:C56) -> 0 | D57: =SUM(D54:D56) -> 0 | E57: =SUM(E54:E56) -> 0 | F57: =SUM(F54:F56) -> 0 | G57: =SUM(G54:G56) -> 0 | H57: =SUM(H54:H56) -> 0 | I57: =SUM(I54:I56) -> 0 | ... L57: =SUM(L54:L56) -> 0
G58: BISTRO TILL TOTAL | J58: =SUM(I57+J57+H57+G57)-C57-E57 -> 0

Sheet Tue diary
A1: Republic Hotel
A2: =Tue!L3 -> 46056
A5: Summary | B5: Tuesday | C5: Week to date | F5: Bars | G5: =SUM(G6:G9) -> 0
A6: Gaming Turnover | B6: =Takings!B25 -> 0 | C6: =SUM(Takings!B24:B25) -> 0 | F6: Public | G6: =Takings!C6 -> 0
A7: Gaming Gross | B7: =Takings!C25 -> 0 | C7: =SUM(Takings!C24:C25) -> 0 | F7: Bistro | G7: =Takings!D6 -> 0
A8: Gaming Net | B8: =Takings!I6 -> 0 | C8: =SUM(Takings!I5:I6) -> 0 | F8: Sports | G8: =Takings!E6 -> 0
A9: Dragon Link (50K) | F9: Taylors | G9: =Takings!F6 -> 0
A10: Dragon Train (20K)
A11: Fortune Hearts (25K)
A12: Dragon Rush (90K)
A13: Dragon Link (90K)
A14: Thunder Empire (50K) | F14: Bistro & Food Service
A15: Power Panther (12K) | F15: Day Covers | H15: Night Covers
A16: Bars | B16: =Takings!C46 -> 0 | C16: =SUM(Takings!B46:C46) -> 0 | F16: LUNCH Service Feedback
A17: Food | B17: =Takings!C49 -> 0 | C17: =SUM(Takings!B49:C49) -> 0
A18: Retail | B18: =Takings!H6 -> 0 | C18: =SUM(Takings!H5:H6) -> 0 | F18: Dinner Service Feedback
A19: TAB | B19: =Takings!L38 -> 0 | C19: =SUM(Takings!L37:L38) -> 0
F20: Public Bar
B21: DAY | C21: MID | D21: CLOSE | F21: Food | G21: =Tue!C22+Tue!C28 -> 0 | H21: Bev | I21: =Tue!J29 -> 0
A22: Managers Name | F22: Day
B23: GAMING
A24: Day turnover up to 6pm | B24: =G75 -> 0 | C24: Staff | F24: Evening
A25: How was the days trade
A26: Who were your big punters | F26: Late Night
A27: Large payouts/links & to whom
A28: Night turnover after 6pm | B28: =B6-B24 -> 0 | C28: Staff | F28: Bistro
A29: How was the night trade | F29: Food | G29: =Tue!C8 -> 0 | H29: Bev | I29: =Tue!J9 -> 0
A30: Who were your big punters | F30: Day
A31: Large payouts/links & to whom
B32: LINKS IF WON | F32: Evening
A33: What Link did they win
A34: How much was the Link | F34: Late Night
A35: What machine number
A36: How much were they betting | F36: Sports Bar
A37: Are they a regular | F37: Food | G37: =Tue!C15 -> 0 | H37: Bev | I37: =Tue!J16 -> 0
B38: AUSTRAC REPORTING | F38: Day
A39: Any Suspicious Customers
A40: Cash In to Turnover Ratio | B40: =Takings!B25/Takings!E25 -> #DIV/0! | F40: Evening
A41: Checked by
B42: TAB | F42: Late Night
A43: How was day trade
A44: How was night trade | F44: Taylors Rooftop
A45: Feedback/Issues | F45: Food | G45: =Tue!C36+Tue!C42 -> 0 | H45: Bev | I45: =Tue!J43 -> 0
F46: Day
B47: RETAIL
A48: How was day trade | F48: Evening
A49: How was night trade
B50: WHAT'S ON | F50: Late Night
A51: Event name(s)
A52: How many people | C52: Jackpot $
A53: Feedback
B54: FUNCTIONS | F54: Food Service
A55: Type of function | F55: Time | G55: Food served | J55: Portions Taken
A56: How many people
A57: Feedback
B58: CASHING UP
A59: Enter Safe Variance Amount
A60: Explanation if (+/- $20)
B61: SECURITY
A62: Any issues
A64: Who & how were guards
B65: COMPLIANCE | F65: GAMING | H65: HOURLY | I65: PATRON | J65: ROOM
A66: STAR COMPLIANCE FILLED IN (Y/N) | F66: ROOM | G66: TURNOVER | H66: TURNOVER | I66: NUMBERS | J66: TEMP
A67: CCTV CHECK (Y/N) | F67: 10am | J67: 23
A68: Police visits or incidents | F68: 11am | H68: =G68-G67 -> 0 | J68: 23
A69: OLGR visits or incidents | F69: 12pm | H69: =G69-G68 -> 0 | J69: 23
B70: OH&S | F70: 1pm | H70: =G70-G69 -> 0 | J70: 23
A71: Any injuries? | F71: 2pm | H71: =G71-G70 -> 0 | J71: 23
A72: Treatment provided (Sent to Dr?) | F72: 3pm | H72: =G72-G71 -> 0 | J72: 23
F73: 4pm | H73: =G73-G72 -> 0 | J73: 23
F74: 5pm | H74: =G74-G73 -> 0 | J74: 23
F75: 6pm | H75: =G75-G74 -> 0 | J75: 23
F76: 7pm | H76: =G76-G75 -> 0 | J76: 23
F77: 8pm | H77: =G77-G76 -> 0 | J77: 23
F78: 9pm | H78: =G78-G77 -> 0 | J78: 23
F79: 10pm | H79: =G79-G78 -> 0 | J79: 23
F80: 11pm | H80: =G80-G79 -> 0 | J80: 23
F81: 12am | H81: =G81-G80 -> 0 | J81: 23
F82: 1am | H82: =G82-G81 -> 0 | J82: 23
F83: 2am | H83: =G83-G82 -> 0 | J83: 23
F84: 3am | H84: =G84-G83 -> 0 | J84: 23
F85: 4am | H85: =G85-G84 -> 0 | J85: 23

Sheet Wed
A1: Republic Hotel - Daily Takings
A2: WEDNESDAY
K3: DATE: | L3: =Tue!L3+1 -> 46057 | N3: SUNDRIES | Q3: FOOD
A4: BISTRO | B4: READING | C4: FOOD | D4: TYRO FEE | E4: TIPS | F4: EXPECTED | G4: EFTPOS | H4: AMEX/DINER | I4: ME&U | J4: CASH | K4: VAR (+ / -) | L4: ACCOUNT | Q4: =A4 -> BISTRO | R4: =C8 -> 0
F5: =B5-(D5+L5) -> 0 | K5: =SUM(I5+J5+H5+G5)-F5 -> 0 | Q5: =A11 -> SPORTS BAR | R5: =C15 -> 0
F6: =B6-(D6+L6) -> 0 | K6: =SUM(I6+J6+H6+G6)-F6 -> 0 | Q6: BALCONY | R6: =C22+C28 -> 0
F7: =B7-(D7+L7) -> 0 | K7: =SUM(I7+J7+H7+G7)-F7 -> 0 | N7: TOTAL | O7: =O4+O5+O6 -> 0 | Q7: PUBLIC 1 / 2 | R7: =+C36+C42 -> 0
A8: TOTALS | B8: =SUM(B5:B7) -> 0 | C8: =SUM(C5:C7) -> 0 | D8: =SUM(D5:D7) -> 0 | E8: =SUM(E5:E7) -> 0 | F8: =SUM(F5:F7) -> 0 | G8: =SUM(G5:G7) -> 0 | H8: =SUM(H5:H7) -> 0 | I8: =SUM(I5:I7) -> 0 | J8: =SUM(J5:J7) -> 0 | K8: =SUM(I8+J8+H8+G8)-F8 -> 0 | L8: =SUM(L5:L7) -> 0 | Q8: BISTRO TILL | R8: =C57 -> 0
G9: BISTRO TOTAL | J9: =SUM(I8+J8+H8+G8)-C8-E8 -> 0 | Q9: TOTAL | R9: =SUM(R4:R8) -> 0
N10: TAB
A11: SPORTS BAR | B11: READING | C11: FOOD | D11: TYRO FEE | E11: TIPS | F11: EXPECTED | G11: EFTPOS | H11: AMEX/DINER | I11: ME&U | J11: CASH | K11: VAR (+ / -) | L11: ACCOUNT | N11: SALES | Q11: POKIES
F12: =B12-(D12+L12) -> 0 | K12: =SUM(I12+J12+H12+G12)-F12 -> 0 | N12: TERMINAL | Q12: CASH BOX
F13: =B13-(D13+L13) -> 0 | K13: =SUM(I13+J13+H13+G13)-F13 -> 0 | N13: EBET 1 | Q13: TICKET IN
F14: =B14-(D14+L14) -> 0 | K14: =SUM(I14+J14+H14+G14)-F14 -> 0 | N14: EBET 2 | Q14: CASH IN | R14: =R12-R13 -> 0
A15: TOTALS | B15: =SUM(B12:B14) -> 0 | C15: =SUM(C12:C14) -> 0 | D15: =SUM(D12:D14) -> 0 | E15: =SUM(E12:E14) -> 0 | F15: =SUM(F12:F14) -> 0 | G15: =SUM(G12:G14) -> 0 | H15: =SUM(H12:H14) -> 0 | I15: =SUM(I12:I14) -> 0 | ... L15: =SUM(L12:L14) -> 0 | N15: TOTAL | O15: =SUM(O12:O14) -> 0 | Q15: MONEY OUT
G16: SPORTS BAR TOTAL | J16: =SUM(I15+J15+H15+G15)-C15-E15 -> 0 | N16: LIABILITY | Q16: LINK AUTO
N17: TERMINAL | Q17: LINK MAN
A18: PUBLIC 1 | B18: READING | C18: FOOD | D18: TYRO FEE | E18: TIPS | F18: EXPECTED | G18: EFTPOS | H18: AMEX/DINER | I18: ME&U | J18: CASH | K18: VAR (+ / -) | L18: ACCOUNT | N18: EBET 1 | Q18: C/CREDITS
F19: =B19-(D19+L19) -> 0 | K19: =SUM(I19+J19+H19+G19)-F19 -> 0 | N19: EBET 2 | Q19: NET | R19: =R12-R15-R17-R18 -> 0
F20: =B20-(D20+L20) -> 0 | K20: =SUM(I20+J20+H20+G20)-F20 -> 0 | N20: TOTAL | O20: =SUM(O17:O19) -> 0 | Q20: TURNOVER
F21: =B21-(D21+L21) -> 0 | K21: =SUM(I21+J21+H21+G21)-F21 -> 0
A22: TOTALS | B22: =SUM(B19:B21) -> 0 | C22: =SUM(C19:C21) -> 0 | D22: =SUM(D19:D21) -> 0 | E22: =SUM(E19:E21) -> 0 | F22: =SUM(F19:F21) -> 0 | G22: =SUM(G19:G21) -> 0 | H22: =SUM(H19:H21) -> 0 | I22: =SUM(I19:I21) -> 0 | ... L22: =SUM(L19:L21) -> 0 | N22: EFTPOS
N23: =A11 -> SPORTS BAR | O23: =G15 -> 0 | Q23: TOTALS
A24: PUBLIC 2/GAMING | B24: READING | C24: FOOD | D24: TYRO FEE | E24: TIPS | F24: EXPECTED | G24: EFTPOS | H24: AMEX/DINER | I24: ME&U | J24: CASH | K24: VAR (+ / -) | L24: ACCOUNT | N24: =A4 -> BISTRO | O24: =G8 -> 0 | Q24: RECEIPTS | R24: =SUM(J29,J51,O7,J43,J16,J9,R19,J58,R9) -> 0
F25: =B25-(D25+L25) -> 0 | K25: =SUM(I25+J25+H25+G25)-F25 -> 0 | N25: B/SHOP | O25: =G50 -> 0 | Q25: GST | R25: =ROUND(+R24/11,2) -> 0
F26: =B26-(D26+L26) -> 0 | K26: =SUM(I26+J26+H26+G26)-F26 -> 0 | N26: PUBLIC 1 | O26: =G22 -> 0 | Q26: ATM | R26: =R39 -> 0
F27: =B27-(D27+L27) -> 0 | K27: =SUM(I27+J27+H27+G27)-F27 -> 0 | N27: PUBLIC 2 | O27: =G28 -> 0 | Q27: ME&U | R27: =I57+I42+I36+I28+I22+I15+I8 -> 0
A28: TOTALS | B28: =SUM(B25:B27) -> 0 | C28: =SUM(C25:C27) -> 0 | D28: =SUM(D25:D27) -> 0 | E28: =SUM(E25:E27) -> 0 | F28: =SUM(F25:F27) -> 0 | G28: =SUM(G25:G27) -> 0 | H28: =SUM(H25:H27) -> 0 | I28: =SUM(I25:I27) -> 0 | ... L28: =SUM(L25:L27) -> 0 | N28: ROOF TOP 1 | O28: =G36 -> 0 | Q28: EFTPOS | R28: =O31 -> 0
G29: PUBLIC BAR TOTAL | J29: =SUM(G22+H22+I22+J22)+(I28+J28+H28+G28)-C28-E28-C22-E22 -> 0 | N29: ROOF TOP 2 | O29: =G42 -> 0 | Q29: BANKING | R29: =R24-(R28+R26+R27) -> 0
N30: BISTRO | O30: =G57 -> 0
A31: TAYLORS BAR | N31: TOTAL | O31: =SUM(O23:O30) -> 0 | Q31: TAKING TIN | R31: =J8+J15+J22+J28+J36+J42+J50+J57 -> 0
A32: ROOF TOP 1 | B32: READING | C32: FOOD | D32: TYRO FEE | E32: TIPS | F32: EXPECTED | G32: EFTPOS | H32: AMEX/DINER | I32: ME&U | J32: CASH | K32: VAR (+ / -) | L32: ACCOUNT
F33: =B33-(D33+L33) -> 0 | K33: =SUM(I33+J33+H33+G33)-F33 -> 0 | Q33: TAB (ATM)
F34: =B34-(D34+L34) -> 0 | K34: =SUM(I34+J34+H34+G34)-F34 -> 0
F35: =B35-(D35+L35) -> 0 | K35: =SUM(I35+J35+H35+G35)-F35 -> 0
A36: TOTALS | B36: =SUM(B33:B35) -> 0 | C36: =SUM(C33:C35) -> 0 | D36: =SUM(D33:D35) -> 0 | E36: =SUM(E33:E35) -> 0 | F36: =SUM(F33:F35) -> 0 | G36: =SUM(G33:G35) -> 0 | H36: =SUM(H33:H35) -> 0 | I36: =SUM(I33:I35) -> 0 | ... L36: =SUM(L33:L35) -> 0 | Q36: ATM REFILL
Q37: ATM 1
A38: ROOF TOP 2 | B38: READING | C38: FOOD | D38: TYRO FEE | E38: TIPS | F38: EXPECTED | G38: EFTPOS | H38: AMEX/DINER | I38: ME&U | J38: CASH | K38: VAR (+ / -) | L38: ACCOUNT | Q38: ATM 2
F39: =B39-(D39+L39) -> 0 | K39: =SUM(I39+J39+H39+G39)-F39 -> 0 | Q39: TOTAL | R39: =SUM(R37:R38) -> 0
F40: =B40-(D40+L40) -> 0 | K40: =SUM(I40+J40+H40+G40)-F40 -> 0
F41: =B41-(D41+L41) -> 0 | K41: =SUM(I41+J41+H41+G41)-F41 -> 0
A42: TOTALS | B42: =SUM(B39:B41) -> 0 | C42: =SUM(C39:C41) -> 0 | D42: =SUM(D39:D41) -> 0 | E42: =SUM(E39:E41) -> 0 | F42: =SUM(F39:F41) -> 0 | G42: =SUM(G39:G41) -> 0 | H42: =SUM(H39:H41) -> 0 | I42: =SUM(I39:I41) -> 0 | ... L42: =SUM(L39:L41) -> 0
G43: ROOF TOP TOTAL | J43: =SUM(G36+H36+I36+J36)+(I42+J42+H42+G42)-C36-C42-E36-E42 -> 0
A45: BOTTLE SHOP | B45: READING | C45: TYRO FEE | D45: TYRO FEE | E45: TIPS | F45: EXPECTED | G45: EFTPOS | H45: AMEX/DINER | I45: ME&U | J45: CASH | K45: VAR (+ / -) | L45: ACCOUNT
F46: =B46-(D46+L46) -> 0 | K46: =SUM(I46+J46+H46+G46)-F46 -> 0
F47: =B47-(D47+L47) -> 0 | K47: =SUM(I47+J47+H47+G47)-F47 -> 0
F48: =B48-(D48+L48) -> 0 | K48: =SUM(I48+J48+H48+G48)-F48 -> 0
F49: =B49-(D49+L49) -> 0 | K49: =SUM(I49+J49+H49+G49)-F49 -> 0
A50: TOTALS | B50: =SUM(B46:B49) -> 0 | C50: =SUM(C46:C49) -> 0 | D50: =SUM(D46:D49) -> 0 | E50: =SUM(E46:E49) -> 0 | F50: =SUM(F46:F49) -> 0 | G50: =SUM(G46:G49) -> 0 | H50: =SUM(H46:H49) -> 0 | I50: =SUM(I46:I49) -> 0 | ... L50: =SUM(L46:L49) -> 0
G51: BOTTLE SHOP TOTAL | J51: =SUM(I50+J50+H50+G50)-E50 -> 0
A53: BISTRO TILL | B53: READING | C53: FOOD | D53: TYRO FEE | E53: TIPS | F53: EXPECTED | G53: EFTPOS | H53: AMEX/DINER | I53: ME&U | J53: CASH | K53: VAR (+ / -) | L53: ACCOUNT
F54: =B54-(D54+L54) -> 0 | K54: =SUM(I54+J54+H54+G54)-F54 -> 0
F55: =B55-(D55+L55) -> 0 | K55: =SUM(I55+J55+H55+G55)-F55 -> 0
F56: =B56-(D56+L56) -> 0 | K56: =SUM(I56+J56+H56+G56)-F56 -> 0
A57: TOTALS | B57: =SUM(B54:B56) -> 0 | C57: =SUM(C54:C56) -> 0 | D57: =SUM(D54:D56) -> 0 | E57: =SUM(E54:E56) -> 0 | F57: =SUM(F54:F56) -> 0 | G57: =SUM(G54:G56) -> 0 | H57: =SUM(H54:H56) -> 0 | I57: =SUM(I54:I56) -> 0 | ... L57: =SUM(L54:L56) -> 0
G58: BISTRO TILL TOTAL | J58: =SUM(I57+J57+H57+G57)-C57-E57 -> 0

Sheet Wed diary
A1: Republic Hotel
A2: =Wed!L3 -> 46057
A3: Weather -
A5: Summary | B5: Wednesday | C5: Week to date | F5: Bars | G5: =SUM(G6:G9) -> 0
A6: Gaming Turnover | B6: =Takings!B26 -> 0 | C6: =SUM(Takings!B24:B26) -> 0 | F6: Public | G6: =Takings!C7 -> 0
A7: Gaming Gross | B7: =Takings!C26 -> 0 | C7: =SUM(Takings!C24:C26) -> 0 | F7: Bistro | G7: =Takings!D7 -> 0
A8: Gaming Net | B8: =Takings!I7 -> 0 | C8: =SUM(Takings!I5:I7) -> 0 | F8: Sports | G8: =Takings!E7 -> 0
A9: Dragon Link (50K) | F9: Taylors | G9: =Takings!F7 -> 0
A10: Dragon Train (20K)
A11: Fortune Hearts (25K)
A12: Dragon Rush (90K)
A13: Dragon Link (90K)
A14: Thunder Empire (50K) | F14: Bistro & Food Service
A15: Power Panther (12K) | F15: Day Covers | H15: Night Covers
A16: Bars | B16: =Takings!D46 -> 0 | C16: =SUM(Takings!B46:D46) -> 0 | F16: LUNCH Service Feedback
A17: Food | B17: =Takings!D49 -> 0 | C17: =SUM(Takings!B49:D49) -> 0
A18: Retail | B18: =Takings!H7 -> 0 | C18: =SUM(Takings!H5:H7) -> 0 | F18: Dinner Service Feedback
A19: TAB | B19: =Takings!L39 -> 0 | C19: =SUM(Takings!L37:L39) -> 0
F20: Public Bar
B21: DAY | C21: MID | D21: CLOSE | F21: Food | G21: =Wed!C22+Wed!C28 -> 0 | H21: Bev | I21: =Wed!J29 -> 0
A22: Managers Name | F22: Day
B23: GAMING
A24: Day turnover up to 6pm | B24: =G75 -> 0 | C24: Staff | F24: Evening
A25: How was the days trade
A26: Who were your big punters | F26: Late Night
A27: Large payouts/links & to whom
A28: Night turnover after 6pm | B28: =B6-B24 -> 0 | C28: Staff | F28: Bistro
A29: How was the night trade | F29: Food | G29: =Wed!C8 -> 0 | H29: Bev | I29: =Wed!J9 -> 0
A30: Who were your big punters | F30: Day
A31: Large payouts/links & to whom
B32: LINKS IF WON | F32: Evening
A33: What Link did they win
A34: How much was the Link | F34: Late Night
A35: What machine number
A36: How much were they betting | F36: Sports Bar
A37: Are they a regular | F37: Food | G37: =Wed!C15 -> 0 | H37: Bev | I37: =Wed!J16 -> 0
B38: AUSTRAC REPORTING | F38: Day
A39: Any Suspicious Customers
A40: Cash In to Turnover Ratio | B40: =Takings!B26/Takings!E26 -> #DIV/0! | F40: Evening
A41: Checked by
B42: TAB | F42: Late Night
A43: How was day trade
A44: How was night trade | F44: Taylors Rooftop
A45: Feedback/Issues | F45: Food | G45: =Wed!C36+Wed!C42 -> 0 | H45: Bev | I45: =Wed!J43 -> 0
F46: Day
B47: RETAIL
A48: How was day trade | F48: Evening
A49: How was night trade
B50: WHAT'S ON | F50: Late Night
A51: Event name(s)
A52: How many people | C52: Jackpot $
A53: Feedback
B54: FUNCTIONS | F54: Food Service
A55: Type of function | F55: Time | G55: Food served | J55: Portions Taken
A56: How many people
A57: Feedback
B58: CASHING UP
A59: Enter Safe Variance Amount
A60: Explanation if (+/- $20)
B61: SECURITY
A62: Any issues
A64: Who & how were guards
B65: COMPLIANCE | F65: GAMING | H65: HOURLY | I65: PATRON | J65: ROOM
A66: STAR COMPLIANCE FILLED IN (Y/N) | F66: ROOM | G66: TURNOVER | H66: TURNOVER | I66: NUMBERS | J66: TEMP
A67: CCTV CHECK (Y/N) | F67: 10am | J67: 23
A68: Police visits or incidents | F68: 11am | H68: =G68-G67 -> 0 | J68: 23
A69: OLGR visits or incidents | F69: 12pm | H69: =G69-G68 -> 0 | J69: 23
B70: OH&S | F70: 1pm | H70: =G70-G69 -> 0 | J70: 23
A71: Any injuries? | F71: 2pm | H71: =G71-G70 -> 0 | J71: 23
A72: Treatment provided (Sent to Dr?) | F72: 3pm | H72: =G72-G71 -> 0 | J72: 23
F73: 4pm | H73: =G73-G72 -> 0 | J73: 23
F74: 5pm | H74: =G74-G73 -> 0 | J74: 23
F75: 6pm | H75: =G75-G74 -> 0 | J75: 23
F76: 7pm | H76: =G76-G75 -> 0 | J76: 23
F77: 8pm | H77: =G77-G76 -> 0 | J77: 23
F78: 9pm | H78: =G78-G77 -> 0 | J78: 23
F79: 10pm | H79: =G79-G78 -> 0 | J79: 23
F80: 11pm | H80: =G80-G79 -> 0 | J80: 23
F81: 12am | H81: =G81-G80 -> 0 | J81: 23
F82: 1am | H82: =G82-G81 -> 0 | J82: 23
F83: 2am | H83: =G83-G82 -> 0 | J83: 23
F84: 3am | H84: =G84-G83 -> 0 | J84: 23
F85: 4am | H85: =G85-G84 -> 0 | J85: 23

Sheet Thu
A1: Republic Hotel - Daily Takings
A2: THURSDAY
K3: DATE: | L3: =Wed!L3+1 -> 46058 | N3: SUNDRIES | Q3: FOOD
A4: BISTRO | B4: READING | C4: FOOD | D4: TYRO FEE | E4: TIPS | F4: EXPECTED | G4: EFTPOS | H4: AMEX/DINER | I4: ME&U | J4: CASH | K4: VAR (+ / -) | L4: ACCOUNT | Q4: =A4 -> BISTRO | R4: =C8 -> 0
F5: =B5-(D5+L5) -> 0 | K5: =SUM(I5+J5+H5+G5)-F5 -> 0 | Q5: =A11 -> SPORTS BAR | R5: =C15 -> 0
F6: =B6-(D6+L6) -> 0 | K6: =SUM(I6+J6+H6+G6)-F6 -> 0 | Q6: BALCONY | R6: =C22+C28 -> 0
F7: =B7-(D7+L7) -> 0 | K7: =SUM(I7+J7+H7+G7)-F7 -> 0 | N7: TOTAL | O7: =O4+O5+O6 -> 0 | Q7: PUBLIC 1 / 2 | R7: =+C36+C42 -> 0
A8: TOTALS | B8: =SUM(B5:B7) -> 0 | C8: =SUM(C5:C7) -> 0 | D8: =SUM(D5:D7) -> 0 | E8: =SUM(E5:E7) -> 0 | F8: =SUM(F5:F7) -> 0 | G8: =SUM(G5:G7) -> 0 | H8: =SUM(H5:H7) -> 0 | I8: =SUM(I5:I7) -> 0 | J8: =SUM(J5:J7) -> 0 | K8: =SUM(I8+J8+H8+G8)-F8 -> 0 | L8: =SUM(L5:L7) -> 0 | Q8: BISTRO TILL | R8: =C57 -> 0
G9: BISTRO TOTAL | J9: =SUM(I8+J8+H8+G8)-C8-E8 -> 0 | Q9: TOTAL | R9: =SUM(R4:R8) -> 0
N10: TAB
A11: SPORTS BAR | B11: READING | C11: FOOD | D11: TYRO FEE | E11: TIPS | F11: EXPECTED | G11: EFTPOS | H11: AMEX/DINER | I11: ME&U | J11: CASH | K11: VAR (+ / -) | L11: ACCOUNT | N11: SALES | Q11: POKIES
F12: =B12-(D12+L12) -> 0 | K12: =SUM(I12+J12+H12+G12)-F12 -> 0 | N12: TERMINAL | Q12: CASH BOX
F13: =B13-(D13+L13) -> 0 | K13: =SUM(I13+J13+H13+G13)-F13 -> 0 | N13: EBET 1 | Q13: TICKET IN
F14: =B14-(D14+L14) -> 0 | K14: =SUM(I14+J14+H14+G14)-F14 -> 0 | N14: EBET 2 | Q14: CASH IN | R14: =R12-R13 -> 0
A15: TOTALS | B15: =SUM(B12:B14) -> 0 | C15: =SUM(C12:C14) -> 0 | D15: =SUM(D12:D14) -> 0 | E15: =SUM(E12:E14) -> 0 | F15: =SUM(F12:F14) -> 0 | G15: =SUM(G12:G14) -> 0 | H15: =SUM(H12:H14) -> 0 | I15: =SUM(I12:I14) -> 0 | ... L15: =SUM(L12:L14) -> 0 | N15: TOTAL | O15: =SUM(O12:O14) -> 0 | Q15: MONEY OUT
G16: SPORTS BAR TOTAL | J16: =SUM(I15+J15+H15+G15)-C15-E15 -> 0 | N16: LIABILITY | Q16: LINK AUTO
N17: TERMINAL | Q17: LINK MAN
A18: PUBLIC 1 | B18: READING | C18: FOOD | D18: TYRO FEE | E18: TIPS | F18: EXPECTED | G18: EFTPOS | H18: AMEX/DINER | I18: ME&U | J18: CASH | K18: VAR (+ / -) | L18: ACCOUNT | N18: EBET 1 | Q18: C/CREDITS
F19: =B19-(D19+L19) -> 0 | K19: =SUM(I19+J19+H19+G19)-F19 -> 0 | N19: EBET 2 | Q19: NET | R19: =R12-R15-R17-R18 -> 0
F20: =B20-(D20+L20) -> 0 | K20: =SUM(I20+J20+H20+G20)-F20 -> 0 | N20: TOTAL | O20: =SUM(O17:O19) -> 0 | Q20: TURNOVER
F21: =B21-(D21+L21) -> 0 | K21: =SUM(I21+J21+H21+G21)-F21 -> 0
A22: TOTALS | B22: =SUM(B19:B21) -> 0 | C22: =SUM(C19:C21) -> 0 | D22: =SUM(D19:D21) -> 0 | E22: =SUM(E19:E21) -> 0 | F22: =SUM(F19:F21) -> 0 | G22: =SUM(G19:G21) -> 0 | H22: =SUM(H19:H21) -> 0 | I22: =SUM(I19:I21) -> 0 | ... L22: =SUM(L19:L21) -> 0 | N22: EFTPOS
N23: =A11 -> SPORTS BAR | O23: =G15 -> 0 | Q23: TOTALS
A24: PUBLIC 2/GAMING | B24: READING | C24: FOOD | D24: TYRO FEE | E24: TIPS | F24: EXPECTED | G24: EFTPOS | H24: AMEX/DINER | I24: ME&U | J24: CASH | K24: VAR (+ / -) | L24: ACCOUNT | N24: =A4 -> BISTRO | O24: =G8 -> 0 | Q24: RECEIPTS | R24: =SUM(J29,J51,O7,J43,J16,J9,R19,J58,R9) -> 0
F25: =B25-(D25+L25) -> 0 | K25: =SUM(I25+J25+H25+G25)-F25 -> 0 | N25: B/SHOP | O25: =G50 -> 0 | Q25: GST | R25: =ROUND(+R24/11,2) -> 0
F26: =B26-(D26+L26) -> 0 | K26: =SUM(I26+J26+H26+G26)-F26 -> 0 | N26: PUBLIC 1 | O26: =G22 -> 0 | Q26: ATM | R26: =R39 -> 0
F27: =B27-(D27+L27) -> 0 | K27: =SUM(I27+J27+H27+G27)-F27 -> 0 | N27: PUBLIC 2 | O27: =G28 -> 0 | Q27: ME&U | R27: =I57+I42+I36+I28+I22+I15+I8 -> 0
A28: TOTALS | B28: =SUM(B25:B27) -> 0 | C28: =SUM(C25:C27) -> 0 | D28: =SUM(D25:D27) -> 0 | E28: =SUM(E25:E27) -> 0 | F28: =SUM(F25:F27) -> 0 | G28: =SUM(G25:G27) -> 0 | H28: =SUM(H25:H27) -> 0 | I28: =SUM(I25:I27) -> 0 | ... L28: =SUM(L25:L27) -> 0 | N28: ROOF TOP 1 | O28: =G36 -> 0 | Q28: EFTPOS | R28: =O31 -> 0
G29: PUBLIC BAR TOTAL | J29: =SUM(G22+H22+I22+J22)+(I28+J28+H28+G28)-C28-E28-C22-E22 -> 0 | N29: ROOF TOP 2 | O29: =G42 -> 0 | Q29: BANKING | R29: =R24-(R28+R26+R27) -> 0
N30: BISTRO | O30: =G57 -> 0
A31: TAYLORS BAR | N31: TOTAL | O31: =SUM(O23:O30) -> 0 | Q31: TAKING TIN | R31: =J8+J15+J22+J28+J36+J42+J50+J57 -> 0
A32: ROOF TOP 1 | B32: READING | C32: FOOD | D32: TYRO FEE | E32: TIPS | F32: EXPECTED | G32: EFTPOS | H32: AMEX/DINER | I32: ME&U | J32: CASH | K32: VAR (+ / -) | L32: ACCOUNT
F33: =B33-(D33+L33) -> 0 | K33: =SUM(I33+J33+H33+G33)-F33 -> 0 | Q33: TAB (ATM)
F34: =B34-(D34+L34) -> 0 | K34: =SUM(I34+J34+H34+G34)-F34 -> 0
F35: =B35-(D35+L35) -> 0 | K35: =SUM(I35+J35+H35+G35)-F35 -> 0
A36: TOTALS | B36: =SUM(B33:B35) -> 0 | C36: =SUM(C33:C35) -> 0 | D36: =SUM(D33:D35) -> 0 | E36: =SUM(E33:E35) -> 0 | F36: =SUM(F33:F35) -> 0 | G36: =SUM(G33:G35) -> 0 | H36: =SUM(H33:H35) -> 0 | I36: =SUM(I33:I35) -> 0 | ... L36: =SUM(L33:L35) -> 0 | Q36: ATM REFILL
Q37: ATM 1
A38: ROOF TOP 2 | B38: READING | C38: FOOD | D38: TYRO FEE | E38: TIPS | F38: EXPECTED | G38: EFTPOS | H38: AMEX/DINER | I38: ME&U | J38: CASH | K38: VAR (+ / -) | L38: ACCOUNT | Q38: ATM 2
F39: =B39-(D39+L39) -> 0 | K39: =SUM(I39+J39+H39+G39)-F39 -> 0 | Q39: TOTAL | R39: =SUM(R37:R38) -> 0
F40: =B40-(D40+L40) -> 0 | K40: =SUM(I40+J40+H40+G40)-F40 -> 0
F41: =B41-(D41+L41) -> 0 | K41: =SUM(I41+J41+H41+G41)-F41 -> 0
A42: TOTALS | B42: =SUM(B39:B41) -> 0 | C42: =SUM(C39:C41) -> 0 | D42: =SUM(D39:D41) -> 0 | E42: =SUM(E39:E41) -> 0 | F42: =SUM(F39:F41) -> 0 | G42: =SUM(G39:G41) -> 0 | H42: =SUM(H39:H41) -> 0 | I42: =SUM(I39:I41) -> 0 | ... L42: =SUM(L39:L41) -> 0
G43: ROOF TOP TOTAL | J43: =SUM(G36+H36+I36+J36)+(I42+J42+H42+G42)-C36-C42-E36-E42 -> 0
A45: BOTTLE SHOP | B45: READING | C45: TYRO FEE | D45: TYRO FEE | E45: TIPS | F45: EXPECTED | G45: EFTPOS | H45: AMEX/DINER | I45: ME&U | J45: CASH | K45: VAR (+ / -) | L45: ACCOUNT
F46: =B46-(D46+L46) -> 0 | K46: =SUM(I46+J46+H46+G46)-F46 -> 0
F47: =B47-(D47+L47) -> 0 | K47: =SUM(I47+J47+H47+G47)-F47 -> 0
F48: =B48-(D48+L48) -> 0 | K48: =SUM(I48+J48+H48+G48)-F48 -> 0
F49: =B49-(D49+L49) -> 0 | K49: =SUM(I49+J49+H49+G49)-F49 -> 0
A50: TOTALS | B50: =SUM(B46:B49) -> 0 | C50: =SUM(C46:C49) -> 0 | D50: =SUM(D46:D49) -> 0 | E50: =SUM(E46:E49) -> 0 | F50: =SUM(F46:F49) -> 0 | G50: =SUM(G46:G49) -> 0 | H50: =SUM(H46:H49) -> 0 | I50: =SUM(I46:I49) -> 0 | ... L50: =SUM(L46:L49) -> 0
G51: BOTTLE SHOP TOTAL | J51: =SUM(I50+J50+H50+G50)-E50 -> 0
A53: BISTRO TILL | B53: READING | C53: FOOD | D53: TYRO FEE | E53: TIPS | F53: EXPECTED | G53: EFTPOS | H53: AMEX/DINER | I53: ME&U | J53: CASH | K53: VAR (+ / -) | L53: ACCOUNT
F54: =B54-(D54+L54) -> 0 | K54: =SUM(I54+J54+H54+G54)-F54 -> 0
F55: =B55-(D55+L55) -> 0 | K55: =SUM(I55+J55+H55+G55)-F55 -> 0
F56: =B56-(D56+L56) -> 0 | K56: =SUM(I56+J56+H56+G56)-F56 -> 0
A57: TOTALS | B57: =SUM(B54:B56) -> 0 | C57: =SUM(C54:C56) -> 0 | D57: =SUM(D54:D56) -> 0 | E57: =SUM(E54:E56) -> 0 | F57: =SUM(F54:F56) -> 0 | G57: =SUM(G54:G56) -> 0 | H57: =SUM(H54:H56) -> 0 | I57: =SUM(I54:I56) -> 0 | ... L57: =SUM(L54:L56) -> 0
G58: BISTRO TILL TOTAL | J58: =SUM(I57+J57+H57+G57)-C57-E57 -> 0

Sheet Thu diary
A1: Republic Hotel
A2: =Thu!L3 -> 46058
A3: Weather -
A5: Summary | B5: Thursday | C5: Week to date | F5: Bars | G5: =SUM(G6:G9) -> 0
A6: Gaming Turnover | B6: =Takings!B27 -> 0 | C6: =SUM(Takings!B24:B27) -> 0 | F6: Public | G6: =Takings!C8 -> 0
A7: Gaming Gross | B7: =Takings!C27 -> 0 | C7: =SUM(Takings!C24:C27) -> 0 | F7: Bistro | G7: =Takings!D8 -> 0
A8: Gaming Net | B8: =Takings!I8 -> 0 | C8: =SUM(Takings!I5:I8) -> 0 | F8: Sports | G8: =Takings!E8 -> 0
A9: Dragon Link (50K) | F9: Taylors | G9: =Takings!F8 -> 0
A10: Dragon Train (20K)
A11: Fortune Hearts (25K)
A12: Dragon Rush (90K)
A13: Dragon Link (90K)
A14: Thunder Empire (50K) | F14: Bistro & Food Service
A15: Power Panther (12K) | F15: Day Covers | H15: Night Covers
A16: Bars | B16: =Takings!E46 -> 0 | C16: =SUM(Takings!B46:E46) -> 0 | F16: LUNCH Service Feedback
A17: Food | B17: =Takings!E49 -> 0 | C17: =SUM(Takings!B49:E49) -> 0
A18: Retail | B18: =Takings!H8 -> 0 | C18: =SUM(Takings!H5:H8) -> 0 | F18: Dinner Service Feedback
A19: TAB | B19: =Takings!L40 -> 0 | C19: =SUM(Takings!L37:L40) -> 0
F20: Public Bar
B21: DAY | C21: MID | D21: CLOSE | F21: Food | G21: =Thu!C22+Thu!C28 -> 0 | H21: Bev | I21: =Thu!J29 -> 0
A22: Managers Name | F22: Day
B23: GAMING
A24: Day turnover up to 6pm | B24: =G75 -> 0 | C24: Staff | F24: Evening
A25: How was the days trade
A26: Who were your big punters | F26: Late Night
A27: Large payouts/links & to whom
A28: Night turnover after 6pm | B28: =B6-B24 -> 0 | C28: Staff | F28: Bistro
A29: How was the night trade | F29: Food | G29: =Thu!C8 -> 0 | H29: Bev | I29: =Thu!J9 -> 0
A30: Who were your big punters | F30: Day
A31: Large payouts/links & to whom
B32: LINKS IF WON | F32: Evening
A33: What Link did they win
A34: How much was the Link | F34: Late Night
A35: What machine number
A36: How much were they betting | F36: Sports Bar
A37: Are they a regular | F37: Food | G37: =Thu!C15 -> 0 | H37: Bev | I37: =Thu!J16 -> 0
B38: AUSTRAC REPORTING | F38: Day
A39: Any Suspicious Customers
A40: Cash In to Turnover Ratio | B40: =Takings!B27/Takings!E27 -> #DIV/0! | F40: Evening
A41: Checked by
B42: TAB | F42: Late Night
A43: How was day trade
A44: How was night trade | F44: Taylors Rooftop
A45: Feedback/Issues | F45: Food | G45: =Thu!C36+Thu!C42 -> 0 | H45: Bev | I45: =Thu!J43 -> 0
F46: Day
B47: RETAIL
A48: How was day trade | F48: Evening
A49: How was night trade
B50: WHAT'S ON | F50: Late Night
A51: Event name(s)
A52: How many people | C52: Jackpot $
A53: Feedback
B54: FUNCTIONS | F54: Food Service
A55: Type of function | F55: Time | G55: Food served | J55: Portions Taken
A56: How many people
A57: Feedback
B58: CASHING UP
A59: Enter Safe Variance Amount
A60: Explanation if (+/- $20)
B61: SECURITY
A62: Any issues
A64: Who & how were guards
B65: COMPLIANCE | F65: GAMING | H65: HOURLY | I65: PATRON | J65: ROOM
A66: STAR COMPLIANCE FILLED IN (Y/N) | F66: ROOM | G66: TURNOVER | H66: TURNOVER | I66: NUMBERS | J66: TEMP
A67: CCTV CHECK (Y/N) | F67: 10am | J67: 23
A68: Police visits or incidents | F68: 11am | H68: =G68-G67 -> 0 | J68: 23
A69: OLGR visits or incidents | F69: 12pm | H69: =G69-G68 -> 0 | J69: 23
B70: OH&S | F70: 1pm | H70: =G70-G69 -> 0 | J70: 23
A71: Any injuries? | F71: 2pm | H71: =G71-G70 -> 0 | J71: 23
A72: Treatment provided (Sent to Dr?) | F72: 3pm | H72: =G72-G71 -> 0 | J72: 23
F73: 4pm | H73: =G73-G72 -> 0 | J73: 23
F74: 5pm | H74: =G74-G73 -> 0 | J74: 23
F75: 6pm | H75: =G75-G74 -> 0 | J75: 23
F76: 7pm | H76: =G76-G75 -> 0 | J76: 23
F77: 8pm | H77: =G77-G76 -> 0 | J77: 23
F78: 9pm | H78: =G78-G77 -> 0 | J78: 23
F79: 10pm | H79: =G79-G78 -> 0 | J79: 23
F80: 11pm | H80: =G80-G79 -> 0 | J80: 23
F81: 12am | H81: =G81-G80 -> 0 | J81: 23
F82: 1am | H82: =G82-G81 -> 0 | J82: 23
F83: 2am | H83: =G83-G82 -> 0 | J83: 23
F84: 3am | H84: =G84-G83 -> 0 | J84: 23
F85: 4am | H85: =G85-G84 -> 0 | J85: 23

Sheet Fri
A1: Republic Hotel - Daily Takings
A2: FRIDAY
K3: DATE: | L3: =Thu!L3+1 -> 46059 | N3: SUNDRIES | Q3: FOOD
A4: BISTRO | B4: READING | C4: FOOD | D4: TYRO FEE | E4: TIPS | F4: EXPECTED | G4: EFTPOS | H4: AMEX/DINER | I4: ME&U | J4: CASH | K4: VAR (+ / -) | L4: ACCOUNT | Q4: =A4 -> BISTRO | R4: =C8 -> 0
F5: =B5-(D5+L5) -> 0 | K5: =SUM(I5+J5+H5+G5)-F5 -> 0 | Q5: =A11 -> SPORTS BAR | R5: =C15 -> 0
F6: =B6-(D6+L6) -> 0 | K6: =SUM(I6+J6+H6+G6)-F6 -> 0 | Q6: BALCONY | R6: =C22+C28 -> 0
F7: =B7-(D7+L7) -> 0 | K7: =SUM(I7+J7+H7+G7)-F7 -> 0 | N7: TOTAL | O7: =O4+O5+O6 -> 0 | Q7: PUBLIC 1 / 2 | R7: =+C36+C42 -> 0
A8: TOTALS | B8: =SUM(B5:B7) -> 0 | C8: =SUM(C5:C7) -> 0 | D8: =SUM(D5:D7) -> 0 | E8: =SUM(E5:E7) -> 0 | F8: =SUM(F5:F7) -> 0 | G8: =SUM(G5:G7) -> 0 | H8: =SUM(H5:H7) -> 0 | I8: =SUM(I5:I7) -> 0 | J8: =SUM(J5:J7) -> 0 | K8: =SUM(I8+J8+H8+G8)-F8 -> 0 | L8: =SUM(L5:L7) -> 0 | Q8: BISTRO TILL | R8: =C57 -> 0
G9: BISTRO TOTAL | J9: =SUM(I8+J8+H8+G8)-C8-E8 -> 0 | Q9: TOTAL | R9: =SUM(R4:R8) -> 0
N10: TAB
A11: SPORTS BAR | B11: READING | C11: FOOD | D11: TYRO FEE | E11: TIPS | F11: EXPECTED | G11: EFTPOS | H11: AMEX/DINER | I11: ME&U | J11: CASH | K11: VAR (+ / -) | L11: ACCOUNT | N11: SALES | Q11: POKIES
F12: =B12-(D12+L12) -> 0 | K12: =SUM(I12+J12+H12+G12)-F12 -> 0 | N12: TERMINAL | Q12: CASH BOX
F13: =B13-(D13+L13) -> 0 | K13: =SUM(I13+J13+H13+G13)-F13 -> 0 | N13: EBET 1 | Q13: TICKET IN
F14: =B14-(D14+L14) -> 0 | K14: =SUM(I14+J14+H14+G14)-F14 -> 0 | N14: EBET 2 | Q14: CASH IN | R14: =R12-R13 -> 0
A15: TOTALS | B15: =SUM(B12:B14) -> 0 | C15: =SUM(C12:C14) -> 0 | D15: =SUM(D12:D14) -> 0 | E15: =SUM(E12:E14) -> 0 | F15: =SUM(F12:F14) -> 0 | G15: =SUM(G12:G14) -> 0 | H15: =SUM(H12:H14) -> 0 | I15: =SUM(I12:I14) -> 0 | ... L15: =SUM(L12:L14) -> 0 | N15: TOTAL | O15: =SUM(O12:O14) -> 0 | Q15: MONEY OUT
G16: SPORTS BAR TOTAL | J16: =SUM(I15+J15+H15+G15)-C15-E15 -> 0 | N16: LIABILITY | Q16: LINK AUTO
N17: TERMINAL | Q17: LINK MAN
A18: PUBLIC 1 | B18: READING | C18: FOOD | D18: TYRO FEE | E18: TIPS | F18: EXPECTED | G18: EFTPOS | H18: AMEX/DINER | I18: ME&U | J18: CASH | K18: VAR (+ / -) | L18: ACCOUNT | N18: EBET 1 | Q18: C/CREDITS
F19: =B19-(D19+L19) -> 0 | K19: =SUM(I19+J19+H19+G19)-F19 -> 0 | N19: EBET 2 | Q19: NET | R19: =R12-R15-R17-R18 -> 0
F20: =B20-(D20+L20) -> 0 | K20: =SUM(I20+J20+H20+G20)-F20 -> 0 | N20: TOTAL | O20: =SUM(O17:O19) -> 0 | Q20: TURNOVER
F21: =B21-(D21+L21) -> 0 | K21: =SUM(I21+J21+H21+G21)-F21 -> 0
A22: TOTALS | B22: =SUM(B19:B21) -> 0 | C22: =SUM(C19:C21) -> 0 | D22: =SUM(D19:D21) -> 0 | E22: =SUM(E19:E21) -> 0 | F22: =SUM(F19:F21) -> 0 | G22: =SUM(G19:G21) -> 0 | H22: =SUM(H19:H21) -> 0 | I22: =SUM(I19:I21) -> 0 | ... L22: =SUM(L19:L21) -> 0 | N22: EFTPOS
N23: =A11 -> SPORTS BAR | O23: =G15 -> 0 | Q23: TOTALS
A24: PUBLIC 2/GAMING | B24: READING | C24: FOOD | D24: TYRO FEE | E24: TIPS | F24: EXPECTED | G24: EFTPOS | H24: AMEX/DINER | I24: ME&U | J24: CASH | K24: VAR (+ / -) | L24: ACCOUNT | N24: =A4 -> BISTRO | O24: =G8 -> 0 | Q24: RECEIPTS | R24: =SUM(J29,J51,O7,J43,J16,J9,R19,J58,R9) -> 0
F25: =B25-(D25+L25) -> 0 | K25: =SUM(I25+J25+H25+G25)-F25 -> 0 | N25: B/SHOP | O25: =G50 -> 0 | Q25: GST | R25: =ROUND(+R24/11,2) -> 0
F26: =B26-(D26+L26) -> 0 | K26: =SUM(I26+J26+H26+G26)-F26 -> 0 | N26: PUBLIC 1 | O26: =G22 -> 0 | Q26: ATM | R26: =R39 -> 0
F27: =B27-(D27+L27) -> 0 | K27: =SUM(I27+J27+H27+G27)-F27 -> 0 | N27: PUBLIC 2 | O27: =G28 -> 0 | Q27: ME&U | R27: =I57+I42+I36+I28+I22+I15+I8 -> 0
A28: TOTALS | B28: =SUM(B25:B27) -> 0 | C28: =SUM(C25:C27) -> 0 | D28: =SUM(D25:D27) -> 0 | E28: =SUM(E25:E27) -> 0 | F28: =SUM(F25:F27) -> 0 | G28: =SUM(G25:G27) -> 0 | H28: =SUM(H25:H27) -> 0 | I28: =SUM(I25:I27) -> 0 | ... L28: =SUM(L25:L27) -> 0 | N28: ROOF TOP 1 | O28: =G36 -> 0 | Q28: EFTPOS | R28: =O31 -> 0
G29: PUBLIC BAR TOTAL | J29: =SUM(G22+H22+I22+J22)+(I28+J28+H28+G28)-C28-E28-C22-E22 -> 0 | N29: ROOF TOP 2 | O29: =G42 -> 0 | Q29: BANKING | R29: =R24-(R28+R26+R27) -> 0
N30: BISTRO | O30: =G57 -> 0
A31: TAYLORS BAR | N31: TOTAL | O31: =SUM(O23:O30) -> 0 | Q31: TAKING TIN | R31: =J8+J15+J22+J28+J36+J42+J50+J57 -> 0
A32: ROOF TOP 1 | B32: READING | C32: FOOD | D32: TYRO FEE | E32: TIPS | F32: EXPECTED | G32: EFTPOS | H32: AMEX/DINER | I32: ME&U | J32: CASH | K32: VAR (+ / -) | L32: ACCOUNT
F33: =B33-(D33+L33) -> 0 | K33: =SUM(I33+J33+H33+G33)-F33 -> 0 | Q33: TAB (ATM)
F34: =B34-(D34+L34) -> 0 | K34: =SUM(I34+J34+H34+G34)-F34 -> 0
F35: =B35-(D35+L35) -> 0 | K35: =SUM(I35+J35+H35+G35)-F35 -> 0
A36: TOTALS | B36: =SUM(B33:B35) -> 0 | C36: =SUM(C33:C35) -> 0 | D36: =SUM(D33:D35) -> 0 | E36: =SUM(E33:E35) -> 0 | F36: =SUM(F33:F35) -> 0 | G36: =SUM(G33:G35) -> 0 | H36: =SUM(H33:H35) -> 0 | I36: =SUM(I33:I35) -> 0 | ... L36: =SUM(L33:L35) -> 0 | Q36: ATM REFILL
Q37: ATM 1
A38: ROOF TOP 2 | B38: READING | C38: FOOD | D38: TYRO FEE | E38: TIPS | F38: EXPECTED | G38: EFTPOS | H38: AMEX/DINER | I38: ME&U | J38: CASH | K38: VAR (+ / -) | L38: ACCOUNT | Q38: ATM 2
F39: =B39-(D39+L39) -> 0 | K39: =SUM(I39+J39+H39+G39)-F39 -> 0 | Q39: TOTAL | R39: =SUM(R37:R38) -> 0
F40: =B40-(D40+L40) -> 0 | K40: =SUM(I40+J40+H40+G40)-F40 -> 0
F41: =B41-(D41+L41) -> 0 | K41: =SUM(I41+J41+H41+G41)-F41 -> 0
A42: TOTALS | B42: =SUM(B39:B41) -> 0 | C42: =SUM(C39:C41) -> 0 | D42: =SUM(D39:D41) -> 0 | E42: =SUM(E39:E41) -> 0 | F42: =SUM(F39:F41) -> 0 | G42: =SUM(G39:G41) -> 0 | H42: =SUM(H39:H41) -> 0 | I42: =SUM(I39:I41) -> 0 | ... L42: =SUM(L39:L41) -> 0
G43: ROOF TOP TOTAL | J43: =SUM(G36+H36+I36+J36)+(I42+J42+H42+G42)-C36-C42-E36-E42 -> 0
A45: BOTTLE SHOP | B45: READING | C45: TYRO FEE | D45: TYRO FEE | E45: TIPS | F45: EXPECTED | G45: EFTPOS | H45: AMEX/DINER | I45: ME&U | J45: CASH | K45: VAR (+ / -) | L45: ACCOUNT
F46: =B46-(D46+L46) -> 0 | K46: =SUM(I46+J46+H46+G46)-F46 -> 0
F47: =B47-(D47+L47) -> 0 | K47: =SUM(I47+J47+H47+G47)-F47 -> 0
F48: =B48-(D48+L48) -> 0 | K48: =SUM(I48+J48+H48+G48)-F48 -> 0
F49: =B49-(D49+L49) -> 0 | K49: =SUM(I49+J49+H49+G49)-F49 -> 0
A50: TOTALS | B50: =SUM(B46:B49) -> 0 | C50: =SUM(C46:C49) -> 0 | D50: =SUM(D46:D49) -> 0 | E50: =SUM(E46:E49) -> 0 | F50: =SUM(F46:F49) -> 0 | G50: =SUM(G46:G49) -> 0 | H50: =SUM(H46:H49) -> 0 | I50: =SUM(I46:I49) -> 0 | ... L50: =SUM(L46:L49) -> 0
G51: BOTTLE SHOP TOTAL | J51: =SUM(I50+J50+H50+G50)-E50 -> 0
A53: BISTRO TILL | B53: READING | C53: FOOD | D53: TYRO FEE | E53: TIPS | F53: EXPECTED | G53: EFTPOS | H53: AMEX/DINER | I53: ME&U | J53: CASH | K53: VAR (+ / -) | L53: ACCOUNT
F54: =B54-(D54+L54) -> 0 | K54: =SUM(I54+J54+H54+G54)-F54 -> 0
F55: =B55-(D55+L55) -> 0 | K55: =SUM(I55+J55+H55+G55)-F55 -> 0
F56: =B56-(D56+L56) -> 0 | K56: =SUM(I56+J56+H56+G56)-F56 -> 0
A57: TOTALS | B57: =SUM(B54:B56) -> 0 | C57: =SUM(C54:C56) -> 0 | D57: =SUM(D54:D56) -> 0 | E57: =SUM(E54:E56) -> 0 | F57: =SUM(F54:F56) -> 0 | G57: =SUM(G54:G56) -> 0 | H57: =SUM(H54:H56) -> 0 | I57: =SUM(I54:I56) -> 0 | ... L57: =SUM(L54:L56) -> 0
G58: BISTRO TILL TOTAL | J58: =SUM(I57+J57+H57+G57)-C57-E57 -> 0

Sheet Fri diary
A1: Republic Hotel
A2: =Fri!L3 -> 46059
A3: Weather -
A5: Summary | B5: Friday | C5: Week to date | F5: Bars | G5: =SUM(G6:G9) -> 0
A6: Gaming Turnover | B6: =Takings!B28 -> 0 | C6: =SUM(Takings!B24:B28) -> 0 | F6: Public | G6: =Takings!C9 -> 0
A7: Gaming Gross | B7: =Takings!C28 -> 0 | C7: =SUM(Takings!C24:C28) -> 0 | F7: Bistro | G7: =Takings!D9 -> 0
A8: Gaming Net | B8: =Takings!I9 -> 0 | C8: =SUM(Takings!I5:I9) -> 0 | F8: Sports | G8: =Takings!E9 -> 0
A9: Dragon Link (50K) | F9: Taylors | G9: =Takings!F9 -> 0
A10: Dragon Train (20K)
A11: Fortune Hearts (25K)
A12: Dragon Rush (90K)
A13: Dragon Link (90K)
A14: Thunder Empire (50K) | F14: Bistro & Food Service
A15: Power Panther (12K) | F15: Day Covers | H15: Night Covers
A16: Bars | B16: =Takings!F46 -> 0 | C16: =SUM(Takings!B46:F46) -> 0 | F16: LUNCH Service Feedback
A17: Food | B17: =Takings!F49 -> 0 | C17: =SUM(Takings!B49:F49) -> 0
A18: Retail | B18: =Takings!H9 -> 0 | C18: =SUM(Takings!H5:H9) -> 0 | F18: Dinner Service Feedback
A19: TAB | B19: =Takings!L41 -> 0 | C19: =SUM(Takings!L37:L41) -> 0
F20: Public Bar
B21: DAY | C21: MID | D21: CLOSE | F21: Food | G21: =Fri!C22+Fri!C28 -> 0 | H21: Bev | I21: =Fri!J29 -> 0
A22: Managers Name | F22: Day
B23: GAMING
A24: Day turnover up to 6pm | B24: =G75 -> 0 | C24: Staff | F24: Evening
A25: How was the days trade
A26: Who were your big punters | F26: Late Night
A27: Large payouts/links & to whom
A28: Night turnover after 6pm | B28: =B6-B24 -> 0 | C28: Staff | F28: Bistro
A29: How was the night trade | F29: Food | G29: =Fri!C8 -> 0 | H29: Bev | I29: =Fri!J9 -> 0
A30: Who were your big punters | F30: Day
A31: Large payouts/links & to whom
B32: LINKS IF WON | F32: Evening
A33: What Link did they win
A34: How much was the Link | F34: Late Night
A35: What machine number
A36: How much were they betting | F36: Sports Bar
A37: Are they a regular | F37: Food | G37: =Fri!C15 -> 0 | H37: Bev | I37: =Fri!J16 -> 0
B38: AUSTRAC REPORTING | F38: Day
A39: Any Suspicious Customers
A40: Cash In to Turnover Ratio | B40: =Takings!B28/Takings!E28 -> #DIV/0! | F40: Evening
A41: Checked by
B42: TAB | F42: Late Night
A43: How was day trade
A44: How was night trade | F44: Taylors Rooftop
A45: Feedback/Issues | F45: Food | G45: =Fri!C36+Fri!C42 -> 0 | H45: Bev | I45: =Fri!J43 -> 0
F46: Day
B47: RETAIL
A48: How was day trade | F48: Evening
A49: How was night trade
B50: WHAT'S ON | F50: Late Night
A51: Event name(s)
A52: How many people | C52: Jackpot $
A53: Feedback
B54: FUNCTIONS | F54: Food Service
A55: Type of function | F55: Time | G55: Food served | J55: Portions Taken
A56: How many people
A57: Feedback
B58: CASHING UP
A59: Enter Safe Variance Amount
A60: Explanation if (+/- $20)
B61: SECURITY
A62: Any issues
A64: Who & how were guards
B65: COMPLIANCE | F65: GAMING | H65: HOURLY | I65: PATRON | J65: ROOM
A66: STAR COMPLIANCE FILLED IN (Y/N) | F66: ROOM | G66: TURNOVER | H66: TURNOVER | I66: NUMBERS | J66: TEMP
A67: CCTV CHECK (Y/N) | F67: 10am | J67: 23
A68: Police visits or incidents | F68: 11am | H68: =G68-G67 -> 0 | J68: 23
A69: OLGR visits or incidents | F69: 12pm | H69: =G69-G68 -> 0 | J69: 23
B70: OH&S | F70: 1pm | H70: =G70-G69 -> 0 | J70: 23
A71: Any injuries? | F71: 2pm | H71: =G71-G70 -> 0 | J71: 23
A72: Treatment provided (Sent to Dr?) | F72: 3pm | H72: =G72-G71 -> 0 | J72: 23
F73: 4pm | H73: =G73-G72 -> 0 | J73: 23
F74: 5pm | H74: =G74-G73 -> 0 | J74: 23
F75: 6pm | H75: =G75-G74 -> 0 | J75: 23
F76: 7pm | H76: =G76-G75 -> 0 | J76: 23
F77: 8pm | H77: =G77-G76 -> 0 | J77: 23
F78: 9pm | H78: =G78-G77 -> 0 | J78: 23
F79: 10pm | H79: =G79-G78 -> 0 | J79: 23
F80: 11pm | H80: =G80-G79 -> 0 | J80: 23
F81: 12am | H81: =G81-G80 -> 0 | J81: 23
F82: 1am | H82: =G82-G81 -> 0 | J82: 23
F83: 2am | H83: =G83-G82 -> 0 | J83: 23
F84: 3am | H84: =G84-G83 -> 0 | J84: 23
F85: 4am | H85: =G85-G84 -> 0 | J85: 23

Sheet Sat
A1: Republic Hotel - Daily Takings
A2: SATURDAY
K3: DATE: | L3: =Fri!L3+1 -> 46060 | N3: SUNDRIES | Q3: FOOD
A4: BISTRO | B4: READING | C4: FOOD | D4: TYRO FEE | E4: TIPS | F4: EXPECTED | G4: EFTPOS | H4: AMEX/DINER | I4: ME&U | J4: CASH | K4: VAR (+ / -) | L4: ACCOUNT | Q4: =A4 -> BISTRO | R4: =C8 -> 0
F5: =B5-(D5+L5) -> 0 | K5: =SUM(I5+J5+H5+G5)-F5 -> 0 | Q5: =A11 -> SPORTS BAR | R5: =C15 -> 0
F6: =B6-(D6+L6) -> 0 | K6: =SUM(I6+J6+H6+G6)-F6 -> 0 | Q6: BALCONY | R6: =C22+C28 -> 0
F7: =B7-(D7+L7) -> 0 | K7: =SUM(I7+J7+H7+G7)-F7 -> 0 | N7: TOTAL | O7: =O4+O5+O6 -> 0 | Q7: PUBLIC 1 / 2 | R7: =+C36+C42 -> 0
A8: TOTALS | B8: =SUM(B5:B7) -> 0 | C8: =SUM(C5:C7) -> 0 | D8: =SUM(D5:D7) -> 0 | E8: =SUM(E5:E7) -> 0 | F8: =SUM(F5:F7) -> 0 | G8: =SUM(G5:G7) -> 0 | H8: =SUM(H5:H7) -> 0 | I8: =SUM(I5:I7) -> 0 | J8: =SUM(J5:J7) -> 0 | K8: =SUM(I8+J8+H8+G8)-F8 -> 0 | L8: =SUM(L5:L7) -> 0 | Q8: BISTRO TILL | R8: =C57 -> 0
G9: BISTRO TOTAL | J9: =SUM(I8+J8+H8+G8)-C8-E8 -> 0 | Q9: TOTAL | R9: =SUM(R4:R8) -> 0
N10: TAB
A11: SPORTS BAR | B11: READING | C11: FOOD | D11: TYRO FEE | E11: TIPS | F11: EXPECTED | G11: EFTPOS | H11: AMEX/DINER | I11: ME&U | J11: CASH | K11: VAR (+ / -) | L11: ACCOUNT | N11: SALES | Q11: POKIES
F12: =B12-(D12+L12) -> 0 | K12: =SUM(I12+J12+H12+G12)-F12 -> 0 | N12: TERMINAL | Q12: CASH BOX
F13: =B13-(D13+L13) -> 0 | K13: =SUM(I13+J13+H13+G13)-F13 -> 0 | N13: EBET 1 | Q13: TICKET IN
F14: =B14-(D14+L14) -> 0 | K14: =SUM(I14+J14+H14+G14)-F14 -> 0 | N14: EBET 2 | Q14: CASH IN | R14: =R12-R13 -> 0
A15: TOTALS | B15: =SUM(B12:B14) -> 0 | C15: =SUM(C12:C14) -> 0 | D15: =SUM(D12:D14) -> 0 | E15: =SUM(E12:E14) -> 0 | F15: =SUM(F12:F14) -> 0 | G15: =SUM(G12:G14) -> 0 | H15: =SUM(H12:H14) -> 0 | I15: =SUM(I12:I14) -> 0 | ... L15: =SUM(L12:L14) -> 0 | N15: TOTAL | O15: =SUM(O12:O14) -> 0 | Q15: MONEY OUT
G16: SPORTS BAR TOTAL | J16: =SUM(I15+J15+H15+G15)-C15-E15 -> 0 | N16: LIABILITY | Q16: LINK AUTO
N17: TERMINAL | Q17: LINK MAN
A18: PUBLIC 1 | B18: READING | C18: FOOD | D18: TYRO FEE | E18: TIPS | F18: EXPECTED | G18: EFTPOS | H18: AMEX/DINER | I18: ME&U | J18: CASH | K18: VAR (+ / -) | L18: ACCOUNT | N18: EBET 1 | Q18: C/CREDITS
F19: =B19-(D19+L19) -> 0 | K19: =SUM(I19+J19+H19+G19)-F19 -> 0 | N19: EBET 2 | Q19: NET | R19: =R12-R15-R17-R18 -> 0
F20: =B20-(D20+L20) -> 0 | K20: =SUM(I20+J20+H20+G20)-F20 -> 0 | N20: TOTAL | O20: =SUM(O17:O19) -> 0 | Q20: TURNOVER
F21: =B21-(D21+L21) -> 0 | K21: =SUM(I21+J21+H21+G21)-F21 -> 0
A22: TOTALS | B22: =SUM(B19:B21) -> 0 | C22: =SUM(C19:C21) -> 0 | D22: =SUM(D19:D21) -> 0 | E22: =SUM(E19:E21) -> 0 | F22: =SUM(F19:F21) -> 0 | G22: =SUM(G19:G21) -> 0 | H22: =SUM(H19:H21) -> 0 | I22: =SUM(I19:I21) -> 0 | ... L22: =SUM(L19:L21) -> 0 | N22: EFTPOS
N23: =A11 -> SPORTS BAR | O23: =G15 -> 0 | Q23: TOTALS
A24: PUBLIC 2/GAMING | B24: READING | C24: FOOD | D24: TYRO FEE | E24: TIPS | F24: EXPECTED | G24: EFTPOS | H24: AMEX/DINER | I24: ME&U | J24: CASH | K24: VAR (+ / -) | L24: ACCOUNT | N24: =A4 -> BISTRO | O24: =G8 -> 0 | Q24: RECEIPTS | R24: =SUM(J29,J51,O7,J43,J16,J9,R19,J58,R9) -> 0
F25: =B25-(D25+L25) -> 0 | K25: =SUM(I25+J25+H25+G25)-F25 -> 0 | N25: B/SHOP | O25: =G50 -> 0 | Q25: GST | R25: =ROUND(+R24/11,2) -> 0
F26: =B26-(D26+L26) -> 0 | K26: =SUM(I26+J26+H26+G26)-F26 -> 0 | N26: PUBLIC 1 | O26: =G22 -> 0 | Q26: ATM | R26: =R39 -> 0
F27: =B27-(D27+L27) -> 0 | K27: =SUM(I27+J27+H27+G27)-F27 -> 0 | N27: PUBLIC 2 | O27: =G28 -> 0 | Q27: ME&U | R27: =I57+I42+I36+I28+I22+I15+I8 -> 0
A28: TOTALS | B28: =SUM(B25:B27) -> 0 | C28: =SUM(C25:C27) -> 0 | D28: =SUM(D25:D27) -> 0 | E28: =SUM(E25:E27) -> 0 | F28: =SUM(F25:F27) -> 0 | G28: =SUM(G25:G27) -> 0 | H28: =SUM(H25:H27) -> 0 | I28: =SUM(I25:I27) -> 0 | ... L28: =SUM(L25:L27) -> 0 | N28: ROOF TOP 1 | O28: =G36 -> 0 | Q28: EFTPOS | R28: =O31 -> 0
G29: PUBLIC BAR TOTAL | J29: =SUM(G22+H22+I22+J22)+(I28+J28+H28+G28)-C28-E28-C22-E22 -> 0 | N29: ROOF TOP 2 | O29: =G42 -> 0 | Q29: BANKING | R29: =R24-(R28+R26+R27) -> 0
N30: BISTRO | O30: =G57 -> 0
A31: TAYLORS BAR | N31: TOTAL | O31: =SUM(O23:O30) -> 0 | Q31: TAKING TIN | R31: =J8+J15+J22+J28+J36+J42+J50+J57 -> 0
A32: ROOF TOP 1 | B32: READING | C32: FOOD | D32: TYRO FEE | E32: TIPS | F32: EXPECTED | G32: EFTPOS | H32: AMEX/DINER | I32: ME&U | J32: CASH | K32: VAR (+ / -) | L32: ACCOUNT
F33: =B33-(D33+L33) -> 0 | K33: =SUM(I33+J33+H33+G33)-F33 -> 0 | Q33: TAB (ATM)
F34: =B34-(D34+L34) -> 0 | K34: =SUM(I34+J34+H34+G34)-F34 -> 0
F35: =B35-(D35+L35) -> 0 | K35: =SUM(I35+J35+H35+G35)-F35 -> 0
A36: TOTALS | B36: =SUM(B33:B35) -> 0 | C36: =SUM(C33:C35) -> 0 | D36: =SUM(D33:D35) -> 0 | E36: =SUM(E33:E35) -> 0 | F36: =SUM(F33:F35) -> 0 | G36: =SUM(G33:G35) -> 0 | H36: =SUM(H33:H35) -> 0 | I36: =SUM(I33:I35) -> 0 | ... L36: =SUM(L33:L35) -> 0 | Q36: ATM REFILL
Q37: ATM 1
A38: ROOF TOP 2 | B38: READING | C38: FOOD | D38: TYRO FEE | E38: TIPS | F38: EXPECTED | G38: EFTPOS | H38: AMEX/DINER | I38: ME&U | J38: CASH | K38: VAR (+ / -) | L38: ACCOUNT | Q38: ATM 2
F39: =B39-(D39+L39) -> 0 | K39: =SUM(I39+J39+H39+G39)-F39 -> 0 | Q39: TOTAL | R39: =SUM(R37:R38) -> 0
F40: =B40-(D40+L40) -> 0 | K40: =SUM(I40+J40+H40+G40)-F40 -> 0
F41: =B41-(D41+L41) -> 0 | K41: =SUM(I41+J41+H41+G41)-F41 -> 0
A42: TOTALS | B42: =SUM(B39:B41) -> 0 | C42: =SUM(C39:C41) -> 0 | D42: =SUM(D39:D41) -> 0 | E42: =SUM(E39:E41) -> 0 | F42: =SUM(F39:F41) -> 0 | G42: =SUM(G39:G41) -> 0 | H42: =SUM(H39:H41) -> 0 | I42: =SUM(I39:I41) -> 0 | ... L42: =SUM(L39:L41) -> 0
G43: ROOF TOP TOTAL | J43: =SUM(G36+H36+I36+J36)+(I42+J42+H42+G42)-C36-C42-E36-E42 -> 0
A45: BOTTLE SHOP | B45: READING | C45: TYRO FEE | D45: TYRO FEE | E45: TIPS | F45: EXPECTED | G45: EFTPOS | H45: AMEX/DINER | I45: ME&U | J45: CASH | K45: VAR (+ / -) | L45: ACCOUNT
F46: =B46-(D46+L46) -> 0 | K46: =SUM(I46+J46+H46+G46)-F46 -> 0
F47: =B47-(D47+L47) -> 0 | K47: =SUM(I47+J47+H47+G47)-F47 -> 0
F48: =B48-(D48+L48) -> 0 | K48: =SUM(I48+J48+H48+G48)-F48 -> 0
F49: =B49-(D49+L49) -> 0 | K49: =SUM(I49+J49+H49+G49)-F49 -> 0
A50: TOTALS | B50: =SUM(B46:B49) -> 0 | C50: =SUM(C46:C49) -> 0 | D50: =SUM(D46:D49) -> 0 | E50: =SUM(E46:E49) -> 0 | F50: =SUM(F46:F49) -> 0 | G50: =SUM(G46:G49) -> 0 | H50: =SUM(H46:H49) -> 0 | I50: =SUM(I46:I49) -> 0 | ... L50: =SUM(L46:L49) -> 0
G51: BOTTLE SHOP TOTAL | J51: =SUM(I50+J50+H50+G50)-E50 -> 0
A53: BISTRO TILL | B53: READING | C53: FOOD | D53: TYRO FEE | E53: TIPS | F53: EXPECTED | G53: EFTPOS | H53: AMEX/DINER | I53: ME&U | J53: CASH | K53: VAR (+ / -) | L53: ACCOUNT
F54: =B54-(D54+L54) -> 0 | K54: =SUM(I54+J54+H54+G54)-F54 -> 0
F55: =B55-(D55+L55) -> 0 | K55: =SUM(I55+J55+H55+G55)-F55 -> 0
F56: =B56-(D56+L56) -> 0 | K56: =SUM(I56+J56+H56+G56)-F56 -> 0
A57: TOTALS | B57: =SUM(B54:B56) -> 0 | C57: =SUM(C54:C56) -> 0 | D57: =SUM(D54:D56) -> 0 | E57: =SUM(E54:E56) -> 0 | F57: =SUM(F54:F56) -> 0 | G57: =SUM(G54:G56) -> 0 | H57: =SUM(H54:H56) -> 0 | I57: =SUM(I54:I56) -> 0 | ... L57: =SUM(L54:L56) -> 0
G58: BISTRO TILL TOTAL | J58: =SUM(I57+J57+H57+G57)-C57-E57 -> 0

Sheet Sat diary
A1: Republic Hotel
A2: =Sat!L3 -> 46060
A5: Summary | B5: Saturday | C5: Week to date | F5: Bars | G5: =SUM(G6:G9) -> 0
A6: Gaming Turnover | B6: =Takings!B29 -> 0 | C6: =SUM(Takings!B24:B29) -> 0 | F6: Public | G6: =Takings!C10 -> 0
A7: Gaming Gross | B7: =Takings!C29 -> 0 | C7: =SUM(Takings!C24:C29) -> 0 | F7: Bistro | G7: =Takings!D10 -> 0
A8: Gaming Net | B8: =Takings!I10 -> 0 | C8: =SUM(Takings!I5:I10) -> 0 | F8: Sports | G8: =Takings!E10 -> 0
A9: Dragon Link (50K) | F9: Taylors | G9: =Takings!F10 -> 0
A10: Dragon Train (20K)
A11: Fortune Hearts (25K)
A12: Dragon Rush (90K)
A13: Dragon Link (90K)
A14: Thunder Empire (50K) | F14: Bistro & Food Service
A15: Power Panther (12K) | F15: Day Covers | H15: Night Covers
A16: Bars | B16: =Takings!G46 -> 0 | C16: =SUM(Takings!B46:G46) -> 0 | F16: LUNCH Service Feedback
A17: Food | B17: =Takings!G49 -> 0 | C17: =SUM(Takings!B49:G49) -> 0
A18: Retail | B18: =Takings!H10 -> 0 | C18: =SUM(Takings!H5:H10) -> 0 | F18: Dinner Service Feedback
A19: TAB | B19: =Takings!L42 -> 0 | C19: =SUM(Takings!L37:L42) -> 0
F20: Public Bar
B21: DAY | C21: MID | D21: CLOSE | F21: Food | G21: =Sat!C22+Sat!C28 -> 0 | H21: Bev | I21: =Sat!J29 -> 0
A22: Managers Name | F22: Day
B23: GAMING
A24: Day turnover up to 6pm | B24: =G75 -> 0 | C24: Staff | F24: Evening
A25: How was the days trade
A26: Who were your big punters | F26: Late Night
A27: Large payouts/links & to whom
A28: Night turnover after 6pm | B28: =B6-B24 -> 0 | C28: Staff | F28: Bistro
A29: How was the night trade | F29: Food | G29: =Sat!C8 -> 0 | H29: Bev | I29: =Sat!J9 -> 0
A30: Who were your big punters | F30: Day
A31: Large payouts/links & to whom
B32: LINKS IF WON | F32: Evening
A33: What Link did they win
A34: How much was the Link | F34: Late Night
A35: What machine number
A36: How much were they betting | F36: Sports Bar
A37: Are they a regular | F37: Food | G37: =Sat!C15 -> 0 | H37: Bev | I37: =Sat!J16 -> 0
B38: AUSTRAC REPORTING | F38: Day
A39: Any Suspicious Customers
A40: Cash In to Turnover Ratio | B40: =Takings!B29/Takings!E29 -> #DIV/0! | F40: Evening
A41: Checked by
B42: TAB | F42: Late Night
A43: How was day trade
A44: How was night trade | F44: Taylors Rooftop
A45: Feedback/Issues | F45: Food | G45: =Sat!C36+Sat!C42 -> 0 | H45: Bev | I45: =Sat!J43 -> 0
F46: Day
B47: RETAIL
A48: How was day trade | F48: Evening
A49: How was night trade
B50: WHAT'S ON | F50: Late Night
A51: Event name(s)
A52: How many people | C52: Jackpot $
A53: Feedback
B54: FUNCTIONS | F54: Food Service
A55: Type of function | F55: Time | G55: Food served | J55: Portions Taken
A56: How many people
A57: Feedback
B58: CASHING UP
A59: Enter Safe Variance Amount
A60: Explanation if (+/- $20)
B61: SECURITY
A62: Any issues
A64: Who & how were guards
B65: COMPLIANCE | F65: GAMING | H65: HOURLY | I65: PATRON | J65: ROOM
A66: STAR COMPLIANCE FILLED IN (Y/N) | F66: ROOM | G66: TURNOVER | H66: TURNOVER | I66: NUMBERS | J66: TEMP
A67: CCTV CHECK (Y/N) | F67: 10am | J67: 23
A68: Police visits or incidents | F68: 11am | H68: =G68-G67 -> 0 | J68: 23
A69: OLGR visits or incidents | F69: 12pm | H69: =G69-G68 -> 0 | J69: 23
B70: OH&S | F70: 1pm | H70: =G70-G69 -> 0 | J70: 23
A71: Any injuries? | F71: 2pm | H71: =G71-G70 -> 0 | J71: 23
A72: Treatment provided (Sent to Dr?) | F72: 3pm | H72: =G72-G71 -> 0 | J72: 23
F73: 4pm | H73: =G73-G72 -> 0 | J73: 23
F74: 5pm | H74: =G74-G73 -> 0 | J74: 23
F75: 6pm | H75: =G75-G74 -> 0 | J75: 23
F76: 7pm | H76: =G76-G75 -> 0 | J76: 23
F77: 8pm | H77: =G77-G76 -> 0 | J77: 23
F78: 9pm | H78: =G78-G77 -> 0 | J78: 23
F79: 10pm | H79: =G79-G78 -> 0 | J79: 23
F80: 11pm | H80: =G80-G79 -> 0 | J80: 23
F81: 12am | H81: =G81-G80 -> 0 | J81: 23
F82: 1am | H82: =G82-G81 -> 0 | J82: 23
F83: 2am | H83: =G83-G82 -> 0 | J83: 23
F84: 3am | H84: =G84-G83 -> 0 | J84: 23
F85: 4am | H85: =G85-G84 -> 0 | J85: 23

Sheet Sun
A1: Republic Hotel - Daily Takings
A2: SUNDAY
K3: DATE: | L3: =Sat!L3+1 -> 46061 | N3: SUNDRIES | Q3: FOOD
A4: BISTRO | B4: READING | C4: FOOD | D4: TYRO FEE | E4: TIPS | F4: EXPECTED | G4: EFTPOS | H4: AMEX/DINER | I4: ME&U | J4: CASH | K4: VAR (+ / -) | L4: ACCOUNT | N4: TAB COMM | O4: =Takings!M45 -> 0 | Q4: =A4 -> BISTRO | R4: =C8 -> 0
F5: =B5-(D5+L5) -> 0 | K5: =SUM(I5+J5+H5+G5)-F5 -> 0 | Q5: =A11 -> SPORTS BAR | R5: =C15 -> 0
F6: =B6-(D6+L6) -> 0 | K6: =SUM(I6+J6+H6+G6)-F6 -> 0 | Q6: BALCONY | R6: =C22+C28 -> 0
F7: =B7-(D7+L7) -> 0 | K7: =SUM(I7+J7+H7+G7)-F7 -> 0 | N7: TOTAL | O7: =O4+O5+O6 -> 0 | Q7: PUBLIC 1 / 2 | R7: =+C36+C42 -> 0
A8: TOTALS | B8: =SUM(B5:B7) -> 0 | C8: =SUM(C5:C7) -> 0 | D8: =SUM(D5:D7) -> 0 | E8: =SUM(E5:E7) -> 0 | F8: =SUM(F5:F7) -> 0 | G8: =SUM(G5:G7) -> 0 | H8: =SUM(H5:H7) -> 0 | I8: =SUM(I5:I7) -> 0 | J8: =SUM(J5:J7) -> 0 | K8: =SUM(I8+J8+H8+G8)-F8 -> 0 | L8: =SUM(L5:L7) -> 0 | Q8: BISTRO TILL | R8: =C57 -> 0
G9: BISTRO TOTAL | J9: =SUM(I8+J8+H8+G8)-C8-E8 -> 0 | Q9: TOTAL | R9: =SUM(R4:R8) -> 0
N10: TAB
A11: SPORTS BAR | B11: READING | C11: FOOD | D11: TYRO FEE | E11: TIPS | F11: EXPECTED | G11: EFTPOS | H11: AMEX/DINER | I11: ME&U | J11: CASH | K11: VAR (+ / -) | L11: ACCOUNT | N11: SALES | Q11: POKIES
F12: =B12-(D12+L12) -> 0 | K12: =SUM(I12+J12+H12+G12)-F12 -> 0 | N12: TERMINAL | Q12: CASH BOX
F13: =B13-(D13+L13) -> 0 | K13: =SUM(I13+J13+H13+G13)-F13 -> 0 | N13: EBET 1 | Q13: TICKET IN
F14: =B14-(D14+L14) -> 0 | K14: =SUM(I14+J14+H14+G14)-F14 -> 0 | N14: EBET 2 | Q14: CASH IN | R14: =R12-R13 -> 0
A15: TOTALS | B15: =SUM(B12:B14) -> 0 | C15: =SUM(C12:C14) -> 0 | D15: =SUM(D12:D14) -> 0 | E15: =SUM(E12:E14) -> 0 | F15: =SUM(F12:F14) -> 0 | G15: =SUM(G12:G14) -> 0 | H15: =SUM(H12:H14) -> 0 | I15: =SUM(I12:I14) -> 0 | ... L15: =SUM(L12:L14) -> 0 | N15: TOTAL | O15: =SUM(O12:O14) -> 0 | Q15: MONEY OUT
G16: SPORTS TOTAL | J16: =SUM(I15+J15+H15+G15)-C15-E15 -> 0 | N16: LIABILITY | Q16: LINK AUTO
N17: TERMINAL | Q17: LINK MAN
A18: PUBLIC 1 | B18: READING | C18: FOOD | D18: TYRO FEE | E18: TIPS | F18: EXPECTED | G18: EFTPOS | H18: AMEX/DINER | I18: ME&U | J18: CASH | K18: VAR (+ / -) | L18: ACCOUNT | N18: EBET 1 | Q18: C/CREDITS
F19: =B19-(D19+L19) -> 0 | K19: =SUM(I19+J19+H19+G19)-F19 -> 0 | N19: EBET 2 | Q19: NET | R19: =R12-R15-R17-R18 -> 0
F20: =B20-(D20+L20) -> 0 | K20: =SUM(I20+J20+H20+G20)-F20 -> 0 | N20: TOTAL | O20: =SUM(O17:O19) -> 0 | Q20: TURNOVER
F21: =B21-(D21+L21) -> 0 | K21: =SUM(I21+J21+H21+G21)-F21 -> 0
A22: TOTALS | B22: =SUM(B19:B21) -> 0 | C22: =SUM(C19:C21) -> 0 | D22: =SUM(D19:D21) -> 0 | E22: =SUM(E19:E21) -> 0 | F22: =SUM(F19:F21) -> 0 | G22: =SUM(G19:G21) -> 0 | H22: =SUM(H19:H21) -> 0 | I22: =SUM(I19:I21) -> 0 | ... L22: =SUM(L19:L21) -> 0 | N22: EFTPOS
N23: =A11 -> SPORTS BAR | O23: =G15 -> 0 | Q23: TOTALS
A24: PUBLIC 2/GAMING | B24: READING | C24: FOOD | D24: TYRO FEE | E24: TIPS | F24: EXPECTED | G24: EFTPOS | H24: AMEX/DINER | I24: ME&U | J24: CASH | K24: VAR (+ / -) | L24: ACCOUNT | N24: =A4 -> BISTRO | O24: =G8 -> 0 | Q24: RECEIPTS | R24: =SUM(J29,J51,O7,J43,J16,J9,R19,J58,R9) -> 0
F25: =B25-(D25+L25) -> 0 | K25: =SUM(I25+J25+H25+G25)-F25 -> 0 | N25: B/SHOP | O25: =G50 -> 0 | Q25: GST | R25: =ROUND(+R24/11,2) -> 0
F26: =B26-(D26+L26) -> 0 | K26: =SUM(I26+J26+H26+G26)-F26 -> 0 | N26: PUBLIC 1 | O26: =G22 -> 0 | Q26: ATM | R26: =R39 -> 0
F27: =B27-(D27+L27) -> 0 | K27: =SUM(I27+J27+H27+G27)-F27 -> 0 | N27: PUBLIC 2 | O27: =G28 -> 0 | Q27: ME&U | R27: =I57+I42+I36+I28+I22+I15+I8 -> 0
A28: TOTALS | B28: =SUM(B25:B27) -> 0 | C28: =SUM(C25:C27) -> 0 | D28: =SUM(D25:D27) -> 0 | E28: =SUM(E25:E27) -> 0 | F28: =SUM(F25:F27) -> 0 | G28: =SUM(G25:G27) -> 0 | H28: =SUM(H25:H27) -> 0 | I28: =SUM(I25:I27) -> 0 | ... L28: =SUM(L25:L27) -> 0 | N28: ROOF TOP 1 | O28: =G36 -> 0 | Q28: EFTPOS | R28: =O31 -> 0
G29: PUBLIC BAR TOTAL | J29: =SUM(G22+H22+I22+J22)+(I28+J28+H28+G28)-C28-E28-C22-E22 -> 0 | N29: ROOF TOP 2 | O29: =G42 -> 0 | Q29: BANKING | R29: =R24-(R28+R26+R27) -> 0
N30: BISTRO | O30: =G57 -> 0
A31: TAYLORS BAR | N31: TOTAL | O31: =SUM(O23:O30) -> 0 | Q31: TAKING TIN | R31: =J8+J15+J22+J28+J36+J42+J50+J57 -> 0
A32: ROOF TOP 1 | B32: READING | C32: FOOD | D32: TYRO FEE | E32: TIPS | F32: EXPECTED | G32: EFTPOS | H32: AMEX/DINER | I32: ME&U | J32: CASH | K32: VAR (+ / -) | L32: ACCOUNT
F33: =B33-(D33+L33) -> 0 | K33: =SUM(I33+J33+H33+G33)-F33 -> 0 | Q33: TAB (ATM)
F34: =B34-(D34+L34) -> 0 | K34: =SUM(I34+J34+H34+G34)-F34 -> 0
F35: =B35-(D35+L35) -> 0 | K35: =SUM(I35+J35+H35+G35)-F35 -> 0
A36: TOTALS | B36: =SUM(B33:B35) -> 0 | C36: =SUM(C33:C35) -> 0 | D36: =SUM(D33:D35) -> 0 | E36: =SUM(E33:E35) -> 0 | F36: =SUM(F33:F35) -> 0 | G36: =SUM(G33:G35) -> 0 | H36: =SUM(H33:H35) -> 0 | I36: =SUM(I33:I35) -> 0 | ... L36: =SUM(L33:L35) -> 0 | Q36: ATM REFILL
Q37: ATM 1
A38: ROOF TOP 2 | B38: READING | C38: FOOD | D38: TYRO FEE | E38: TIPS | F38: EXPECTED | G38: EFTPOS | H38: AMEX/DINER | I38: ME&U | J38: CASH | K38: VAR (+ / -) | L38: ACCOUNT | Q38: ATM 2
F39: =B39-(D39+L39) -> 0 | K39: =SUM(I39+J39+H39+G39)-F39 -> 0 | Q39: TOTAL | R39: =SUM(R37:R38) -> 0
F40: =B40-(D40+L40) -> 0 | K40: =SUM(I40+J40+H40+G40)-F40 -> 0
F41: =B41-(D41+L41) -> 0 | K41: =SUM(I41+J41+H41+G41)-F41 -> 0
A42: TOTALS | B42: =SUM(B39:B41) -> 0 | C42: =SUM(C39:C41) -> 0 | D42: =SUM(D39:D41) -> 0 | E42: =SUM(E39:E41) -> 0 | F42: =SUM(F39:F41) -> 0 | G42: =SUM(G39:G41) -> 0 | H42: =SUM(H39:H41) -> 0 | I42: =SUM(I39:I41) -> 0 | ... L42: =SUM(L39:L41) -> 0
G43: ROOF TOP TOTAL | J43: =SUM(G36+H36+I36+J36)+(I42+J42+H42+G42)-C36-C42-E36-E42 -> 0
A45: BOTTLE SHOP | B45: READING | C45: TYRO FEE | D45: TYRO FEE | E45: TIPS | F45: EXPECTED | G45: EFTPOS | H45: AMEX/DINER | I45: ME&U | J45: CASH | K45: VAR (+ / -) | L45: ACCOUNT
F46: =B46-(D46+L46) -> 0 | K46: =SUM(I46+J46+H46+G46)-F46 -> 0
F47: =B47-(D47+L47) -> 0 | K47: =SUM(I47+J47+H47+G47)-F47 -> 0
F48: =B48-(D48+L48) -> 0 | K48: =SUM(I48+J48+H48+G48)-F48 -> 0
F49: =B49-(D49+L49) -> 0 | K49: =SUM(I49+J49+H49+G49)-F49 -> 0
A50: TOTALS | B50: =SUM(B46:B49) -> 0 | C50: =SUM(C46:C49) -> 0 | D50: =SUM(D46:D49) -> 0 | E50: =SUM(E46:E49) -> 0 | F50: =SUM(F46:F49) -> 0 | G50: =SUM(G46:G49) -> 0 | H50: =SUM(H46:H49) -> 0 | I50: =SUM(I46:I49) -> 0 | ... L50: =SUM(L46:L49) -> 0
G51: BOTTLE SHOP TOTAL | J51: =SUM(I50+J50+H50+G50)-E50 -> 0
A53: BISTRO TILL | B53: READING | C53: FOOD | D53: TYRO FEE | E53: TIPS | F53: EXPECTED | G53: EFTPOS | H53: AMEX/DINER | I53: ME&U | J53: CASH | K53: VAR (+ / -) | L53: ACCOUNT
F54: =B54-(D54+L54) -> 0 | K54: =SUM(I54+J54+H54+G54)-F54 -> 0
F55: =B55-(D55+L55) -> 0 | K55: =SUM(I55+J55+H55+G55)-F55 -> 0
F56: =B56-(D56+L56) -> 0 | K56: =SUM(I56+J56+H56+G56)-F56 -> 0
A57: TOTALS | B57: =SUM(B54:B56) -> 0 | C57: =SUM(C54:C56) -> 0 | D57: =SUM(D54:D56) -> 0 | E57: =SUM(E54:E56) -> 0 | F57: =SUM(F54:F56) -> 0 | G57: =SUM(G54:G56) -> 0 | H57: =SUM(H54:H56) -> 0 | I57: =SUM(I54:I56) -> 0 | ... L57: =SUM(L54:L56) -> 0
G58: BISTRO TILL TOTAL | J58: =SUM(I57+J57+H57+G57)-C57-E57 -> 0

Sheet Sun diary
A1: Republic Hotel
A2: =Sun!L3 -> 46061
A3: Weather -
A5: Summary | B5: Sunday | C5: Week to date | F5: Bars | G5: =SUM(G6:G9) -> 0
A6: Gaming Turnover | B6: =Takings!B30 -> 0 | C6: =SUM(Takings!B24:B30) -> 0 | F6: Public | G6: =Takings!C11 -> 0
A7: Gaming Gross | B7: =Takings!C30 -> 0 | C7: =SUM(Takings!C24:C30) -> 0 | F7: Bistro | G7: =Takings!D11 -> 0
A8: Gaming Net | B8: =Takings!I11 -> 0 | C8: =SUM(Takings!I5:I11) -> 0 | F8: Sports | G8: =Takings!E11 -> 0
A9: Dragon Link (50K) | F9: Taylors | G9: =Takings!F11 -> 0
A10: Dragon Train (20K)
A11: Fortune Hearts (25K)
A12: Dragon Rush (90K)
A13: Dragon Link (90K)
A14: Thunder Empire (50K) | F14: Bistro & Food Service
A15: Power Panther (12K) | F15: Day Covers | H15: Night Covers
A16: Bars | B16: =Takings!H46 -> 0 | C16: =SUM(Takings!B46:H46) -> 0 | F16: LUNCH Service Feedback
A17: Food | B17: =Takings!H49 -> 0 | C17: =SUM(Takings!B49:H49) -> 0
A18: Retail | B18: =Takings!H11 -> 0 | C18: =SUM(Takings!H5:H11) -> 0 | F18: Dinner Service Feedback
A19: TAB | B19: =Takings!L43 -> 0 | C19: =SUM(Takings!L37:L43) -> 0
F20: Public Bar
B21: DAY | C21: MID | D21: CLOSE | F21: Food | G21: =Sun!C22+Sun!C28 -> 0 | H21: Bev | I21: =Sun!J29 -> 0
A22: Managers Name | F22: Day
B23: GAMING
A24: Day turnover up to 6pm | B24: =G75 -> 0 | C24: Staff | F24: Evening
A25: How was the days trade
A26: Who were your big punters | F26: Late Night
A27: Large payouts/links & to whom
A28: Night turnover after 6pm | B28: =B6-B24 -> 0 | C28: Staff | F28: Bistro
A29: How was the night trade | F29: Food | G29: =Sun!C8 -> 0 | H29: Bev | I29: =Sun!J9 -> 0
A30: Who were your big punters | F30: Day
A31: Large payouts/links & to whom
B32: LINKS IF WON | F32: Evening
A33: What Link did they win
A34: How much was the Link | F34: Late Night
A35: What machine number
A36: How much were they betting | F36: Sports Bar
A37: Are they a regular | F37: Food | G37: =Sun!C15 -> 0 | H37: Bev | I37: =Sun!J16 -> 0
B38: AUSTRAC REPORTING | F38: Day
A39: Any Suspicious Customers
A40: Cash In to Turnover Ratio | B40: =Takings!B30/Takings!E30 -> #DIV/0! | F40: Evening
A41: Checked by
B42: TAB | F42: Late Night
A43: How was day trade
A44: How was night trade | F44: Taylors Rooftop
A45: Feedback/Issues | F45: Food | G45: =Sun!C36+Sun!C42 -> 0 | H45: Bev | I45: =Sun!J43 -> 0
F46: Day
B47: RETAIL
A48: How was day trade | F48: Evening
A49: How was night trade
B50: WHAT'S ON | F50: Late Night
A51: Event name(s)
A52: How many people | C52: Jackpot $
A53: Feedback
B54: FUNCTIONS | F54: Food Service
A55: Type of function | F55: Time | G55: Food served | J55: Portions Taken
A56: How many people
A57: Feedback
B58: CASHING UP
A59: Enter Safe Variance Amount
A60: Explanation if (+/- $20)
B61: SECURITY
A62: Any issues
A64: Who & how were guards
B65: COMPLIANCE | F65: GAMING | H65: HOURLY | I65: PATRON | J65: ROOM
A66: STAR COMPLIANCE FILLED IN (Y/N) | F66: ROOM | G66: TURNOVER | H66: TURNOVER | I66: NUMBERS | J66: TEMP
A67: CCTV CHECK (Y/N) | F67: 10am | J67: 23
A68: Police visits or incidents | F68: 11am | H68: =G68-G67 -> 0 | J68: 23
A69: OLGR visits or incidents | F69: 12pm | H69: =G69-G68 -> 0 | J69: 23
B70: OH&S | F70: 1pm | H70: =G70-G69 -> 0 | J70: 23
A71: Any injuries? | F71: 2pm | H71: =G71-G70 -> 0 | J71: 23
A72: Treatment provided (Sent to Dr?) | F72: 3pm | H72: =G72-G71 -> 0 | J72: 23
F73: 4pm | H73: =G73-G72 -> 0 | J73: 23
F74: 5pm | H74: =G74-G73 -> 0 | J74: 23
F75: 6pm | H75: =G75-G74 -> 0 | J75: 23
F76: 7pm | H76: =G76-G75 -> 0 | J76: 23
F77: 8pm | H77: =G77-G76 -> 0 | J77: 23
F78: 9pm | H78: =G78-G77 -> 0 | J78: 23
F79: 10pm | H79: =G79-G78 -> 0 | J79: 23
F80: 11pm | H80: =G80-G79 -> 0 | J80: 23
F81: 12am | H81: =G81-G80 -> 0 | J81: 23
F82: 1am | H82: =G82-G81 -> 0 | J82: 23
F83: 2am | H83: =G83-G82 -> 0 | J83: 23
F84: 3am | H84: =G84-G83 -> 0 | J84: 23
F85: 4am | H85: =G85-G84 -> 0 | J85: 23

Sheet Takings
F1: Republic Hotel
O2: WEEK ENDING: | P2: =Sun!L3 -> 46061
A3: DATE | B3: DAY | C3: =Mon!A4 -> BISTRO | D3: =Mon!A11 -> SPORTS BAR | E3: PUBLIC | F3: TAYLORS | G3: FOOD | H3: =Mon!A45 -> BOTTLE SHOP | I3: POKIES NET | J3: SUNDRIES | K3: DETAILS | M3: TOTAL | N3: EFT/ATM | O3: BANKED | P3: GST
A5: =A6-1 -> 46055 | B5: MON | C5: =Mon!J9 -> 0 | D5: =Mon!J16 -> 0 | E5: =Mon!J29+Mon!J58 -> 0 | F5: =Mon!J43 -> 0 | G5: =B49 -> 0 | H5: =Mon!J51 -> 0 | I5: =Mon!R19 -> 0 | J5: =Mon!O7 -> 0 | M5: =SUM(C5:J5) -> 0 | N5: =T24 -> 0 | O5: =M5-N5 -> 0 | P5: =M5/11 -> 0
A6: =A7-1 -> 46056 | B6: TUE | C6: =Tue!J9 -> 0 | D6: =Tue!J16 -> 0 | E6: =Tue!J29+Tue!J58 -> 0 | F6: =Tue!J43 -> 0 | G6: =C49 -> 0 | H6: =Tue!J51 -> 0 | I6: =Tue!R19 -> 0 | J6: =Tue!O7 -> 0 | M6: =SUM(C6:J6) -> 0 | N6: =T25 -> 0 | O6: =M6-N6 -> 0 | P6: =M6/11 -> 0
A7: =A8-1 -> 46057 | B7: WED | C7: =Wed!J9 -> 0 | D7: =Wed!J16 -> 0 | E7: =Wed!J29+Wed!J58 -> 0 | F7: =Wed!J43 -> 0 | G7: =D49 -> 0 | H7: =Wed!J51 -> 0 | I7: =Wed!R19 -> 0 | J7: =Wed!O7 -> 0 | M7: =SUM(C7:J7) -> 0 | N7: =T26 -> 0 | O7: =M7-N7 -> 0 | P7: =M7/11 -> 0
A8: =A9-1 -> 46058 | B8: THUR | C8: =Thu!J9 -> 0 | D8: =Thu!J16 -> 0 | E8: =Thu!J29+Thu!J58 -> 0 | F8: =Thu!J43 -> 0 | G8: =E49 -> 0 | H8: =Thu!J51 -> 0 | I8: =Thu!R19 -> 0 | J8: =Thu!O7 -> 0 | M8: =SUM(C8:J8) -> 0 | N8: =T27 -> 0 | O8: =M8-N8 -> 0 | P8: =M8/11 -> 0
A9: =A10-1 -> 46059 | B9: FRI | C9: =Fri!J9 -> 0 | D9: =Fri!J16 -> 0 | E9: =Fri!J29+Fri!J58 -> 0 | F9: =Fri!J43 -> 0 | G9: =F49 -> 0 | H9: =Fri!J51 -> 0 | I9: =Fri!R19 -> 0 | J9: =Fri!O7 -> 0 | M9: =SUM(C9:J9) -> 0 | N9: =T28 -> 0 | O9: =M9-N9 -> 0 | P9: =M9/11 -> 0
A10: =A11-1 -> 46060 | B10: SAT | C10: =Sat!J9 -> 0 | D10: =Sat!J16 -> 0 | E10: =Sat!J29+Sat!J58 -> 0 | F10: =Sat!J43 -> 0 | G10: =G49 -> 0 | H10: =Sat!J51 -> 0 | I10: =Sat!R19 -> 0 | J10: =Sat!O7 -> 0 | M10: =SUM(C10:J10) -> 0 | N10: =T29 -> 0 | O10: =M10-N10 -> 0 | P10: =M10/11 -> 0
A11: =P2 -> 46061 | B11: SUN | C11: =Sun!J9 -> 0 | D11: =Sun!J16 -> 0 | E11: =Sun!J29+Sun!J58 -> 0 | F11: =Sun!J43 -> 0 | G11: =H49 -> 0 | H11: =Sun!J51 -> 0 | I11: =Sun!R19 -> 0 | J11: =Sun!O7 -> 0 | K11: TAB COMMISSION | M11: =SUM(C11:J11) -> 0 | N11: =T30 -> 0 | O11: =M11-N11 -> 0 | P11: =M11/11 -> 0
A12: TOTAL | C12: =SUM(C5:C11) -> 0 | D12: =SUM(D5:D11) -> 0 | E12: =SUM(E5:E11) -> 0 | F12: =SUM(F5:F11) -> 0 | G12: =SUM(G5:G11) -> 0 | H12: =SUM(H5:H11) -> 0 | I12: =SUM(I5:I11) -> 0 | J12: =SUM(J5:J11) -> 0 | M12: =SUM(M5:M11) -> 0 | N12: =SUM(N5:N11) -> 0 | O12: =SUM(O5:O11) -> 0 | P12: =SUM(P5:P11) -> 0
A14: GST | C14: =C12/11 -> 0 | D14: =D12/11 -> 0 | E14: =E12/11 -> 0 | F14: =F12/11 -> 0 | G14: =G12/11 -> 0 | H14: =H12/11 -> 0 | I14: =I12/11 -> 0 | J14: =J12/11 -> 0 | M14: =M12/11 -> 0 | O14: GST CHECK | P14: =M14-P12 -> 0
A16: BALANCE | C16: =C12-C14 -> 0 | D16: =D12-D14 -> 0 | E16: =E12-E14 -> 0 | F16: =F12-F14 -> 0 | G16: =G12-G14 -> 0 | H16: =H12-H14 -> 0 | I16: =I12-I14 -> 0 | J16: =J12-J14 -> 0 | M16: =M12-M14 -> 0
A18: POS
A19: TYRO SURCHARGE | C19: =SUM(Mon!D8+Tue!D8+Wed!D8+Thu!D8+Fri!D8+Sat!D8+Sun!D8) -> 0 | D19: =SUM(Mon!D15+Tue!D15+Wed!D15+Thu!D15+Fri!D15+Sat!D15+Sun!D15) -> 0 | E19: =SUM(Mon!D22+Mon!D28+Tue!D22+Tue!D28+Wed!D22+Wed!D28+Thu!D22+Thu!D28+Fri!D22+Fri!D28+Sat!D22+Sat!D28+Sun!D22+Sun!D28)+(Mon!D57+Tue!D57+Wed!D57+Thu!D57+Fri!D57+Sat!D57+Sun!D57) -> 0 | F19: =SUM(Mon!D36+Mon!D42+Tue!D36+Tue!D42+Wed!D36+Wed!D42+Thu!D36+Thu!D42+Fri!D36+Fri!D42+Sat!D36+Sat!D42+Sun!D36+Sun!D42) -> 0 | G19: =SUM(Mon!D57+Tue!D57+Wed!D57+Thu!D57+Fri!D57+Sat!D57+Sun!D57) -> 0 | H19: =SUM(Mon!D50+Tue!D50+Wed!D50+Thu!D50+Fri!D50+Sat!D50+Sun!D50) -> 0
A20: TILL TOTAL | C20: =C18-C19 -> 0 | D20: =D18-D19 -> 0 | E20: =E18-E19 -> 0 | F20: =F18-F19 -> 0 | G20: =G18-G19 -> 0 | H20: =H18-H19 -> 0
A21: VAR +/- | C21: =C12-C20 -> 0 | D21: =D12-D20 -> 0 | E21: =E12-E20 -> 0 | F21: =F12-F20 -> 0 | G21: =G12 -> 0 | H21: =H12-H20 -> 0
J22: ATM/EFTPOS
A23: GAMING | B23: TURNOVER | C23: GROSS | D23: TICKET IN | E23: CASH IN | F23: PAID OUT | G23: LINKS | H23: NET | J23: =C3 -> BISTRO | K23: =D3 -> SPORTS BAR | L23: B/SHOP | M23: PUBLIC 1 | N23: PUBLIC 2 | O23: ROOF TOP 1 | P23: ROOF TOP 2 | Q23: BISTRO | R23: ME&U | S23: ATM | T23: TOTAL
A24: MON | B24: =Mon!R20 -> 0 | C24: =Mon!R12 -> 0 | D24: =Mon!R13 -> 0 | E24: =Mon!R14 -> 0 | F24: =Mon!R15+Mon!R18 -> 0 | G24: =Mon!R16+Mon!R17 -> 0 | H24: =Mon!R19 -> 0 | J24: =Mon!O24 -> 0 | K24: =Mon!O23 -> 0 | L24: =Mon!O25 -> 0 | M24: =Mon!O26 -> 0 | N24: =Mon!O27 -> 0 | O24: =Mon!O28 -> 0 | P24: =Mon!O29 -> 0 | Q24: =Mon!O30 -> 0 | R24: =Mon!R27 -> 0 | S24: =Mon!R26 -> 0 | T24: =SUM(J24:S24) -> 0
A25: TUE | B25: =Tue!R20 -> 0 | C25: =Tue!R12 -> 0 | D25: =Tue!R13 -> 0 | E25: =Tue!R14 -> 0 | F25: =Tue!R15+Tue!R18 -> 0 | G25: =Tue!R16+Tue!R17 -> 0 | H25: =Tue!R19 -> 0 | J25: =Tue!O24 -> 0 | K25: =Tue!O23 -> 0 | L25: =Tue!O25 -> 0 | M25: =Tue!O26 -> 0 | N25: =Tue!O27 -> 0 | O25: =Tue!O28 -> 0 | P25: =Tue!O29 -> 0 | Q25: =Tue!O30 -> 0 | R25: =Tue!R27 -> 0 | S25: =Tue!R26 -> 0 | T25: =SUM(J25:S25) -> 0
A26: WED | B26: =Wed!R20 -> 0 | C26: =Wed!R12 -> 0 | D26: =Wed!R13 -> 0 | E26: =Wed!R14 -> 0 | F26: =Wed!R15+Wed!R18 -> 0 | G26: =Wed!R16+Wed!R17 -> 0 | H26: =Wed!R19 -> 0 | J26: =Wed!O24 -> 0 | K26: =Wed!O23 -> 0 | L26: =Wed!O25 -> 0 | M26: =Wed!O26 -> 0 | N26: =Wed!O27 -> 0 | O26: =Wed!O28 -> 0 | P26: =Wed!O29 -> 0 | Q26: =Wed!O30 -> 0 | R26: =Wed!R27 -> 0 | S26: =Wed!R26 -> 0 | T26: =SUM(J26:S26) -> 0
A27: THUR | B27: =Thu!R20 -> 0 | C27: =Thu!R12 -> 0 | D27: =Thu!R13 -> 0 | E27: =Thu!R14 -> 0 | F27: =Thu!R15+Thu!R18 -> 0 | G27: =Thu!R16+Thu!R17 -> 0 | H27: =Thu!R19 -> 0 | J27: =Thu!O24 -> 0 | K27: =Thu!O23 -> 0 | L27: =Thu!O25 -> 0 | M27: =Thu!O26 -> 0 | N27: =Thu!O27 -> 0 | O27: =Thu!O28 -> 0 | P27: =Thu!O29 -> 0 | Q27: =Thu!O30 -> 0 | R27: =Thu!R27 -> 0 | S27: =Thu!R26 -> 0 | T27: =SUM(J27:S27) -> 0
A28: FRI | B28: =Fri!R20 -> 0 | C28: =Fri!R12 -> 0 | D28: =Fri!R13 -> 0 | E28: =Fri!R14 -> 0 | F28: =Fri!R15+Fri!R18 -> 0 | G28: =Fri!R16+Fri!R17 -> 0 | H28: =Fri!R19 -> 0 | J28: =Fri!O24 -> 0 | K28: =Fri!O23 -> 0 | L28: =Fri!O25 -> 0 | M28: =Fri!O26 -> 0 | N28: =Fri!O27 -> 0 | O28: =Fri!O28 -> 0 | P28: =Fri!O29 -> 0 | Q28: =Fri!O30 -> 0 | R28: =Fri!R27 -> 0 | S28: =Fri!R26 -> 0 | T28: =SUM(J28:S28) -> 0
A29: SAT | B29: =Sat!R20 -> 0 | C29: =Sat!R12 -> 0 | D29: =Sat!R13 -> 0 | E29: =Sat!R14 -> 0 | F29: =Sat!R15+Sat!R18 -> 0 | G29: =Sat!R16+Sat!R17 -> 0 | H29: =Sat!R19 -> 0 | J29: =Sat!O24 -> 0 | K29: =Sat!O23 -> 0 | L29: =Sat!O25 -> 0 | M29: =Sat!O26 -> 0 | N29: =Sat!O27 -> 0 | O29: =Sat!O28 -> 0 | P29: =Sat!O29 -> 0 | Q29: =Sat!O30 -> 0 | R29: =Sat!R27 -> 0 | S29: =Sat!R26 -> 0 | T29: =SUM(J29:S29) -> 0
A30: SUN | B30: =Sun!R20 -> 0 | C30: =Sun!R12 -> 0 | D30: =Sun!R13 -> 0 | E30: =Sun!R14 -> 0 | F30: =Sun!R15+Sun!R18 -> 0 | G30: =Sun!R16+Sun!R17 -> 0 | H30: =Sun!R19 -> 0 | J30: =Sun!O24 -> 0 | K30: =Sun!O23 -> 0 | L30: =Sun!O25 -> 0 | M30: =Sun!O26 -> 0 | N30: =Sun!O27 -> 0 | O30: =Sun!O28 -> 0 | P30: =Sun!O29 -> 0 | Q30: =Sun!O30 -> 0 | R30: =Sun!R27 -> 0 | S30: =Sun!R26 -> 0 | T30: =SUM(J30:S30) -> 0
A31: TOTALS | B31: =SUM(B24:B30) -> 0 | C31: =SUM(C24:C30) -> 0 | D31: =SUM(D24:D30) -> 0 | E31: =SUM(E24:E30) -> 0 | F31: =SUM(F24:F30) -> 0 | G31: =SUM(G24:G30) -> 0 | H31: =SUM(H24:H30) -> 0 | J31: =SUM(J24:J30) -> 0 | K31: =SUM(K24:K30) -> 0 | L31: =SUM(L24:L30) -> 0 | M31: =SUM(M24:M30) -> 0 | N31: =SUM(N24:N30) -> 0 | O31: =SUM(O24:O30) -> 0 | P31: =SUM(P24:P30) -> 0 | Q31: =SUM(Q24:Q30) -> 0 | ... T31: =SUM(T24:T30) -> 0
A32: GLOBAL
A33: VAR +/- | B33: =B31-B32 -> 0 | C33: =C31-C32 -> 0 | D33: =D31-D32 -> 0 | E33: =E31-E32 -> 0 | F33: =F31-F32 -> 0 | G33: =G31-G32 -> 0
L35: TAB | Q35: TAB
A36: TARGETS | L36: SALES | M36: LIABILITY | N36: CUMM DAILY | O36: VAR | Q36: ATM
A37: DEPT | B37: TARGET | C37: ACTUAL | D37: VAR | E37: REASONS | L37: =Mon!O15 -> 0 | M37: =Mon!O20 -> 0 | O37: =SUM(M36:M37)-N36:N37 -> 0 | Q37: =Mon!R33 -> 0
A38: TURNOVER | B38: 1000000 | C38: =B31 -> 0 | D38: =SUM(C38-B38) -> -1000000 | L38: =Tue!O15 -> 0 | M38: =Tue!O20 -> 0 | O38: =SUM(M37:M38)-N37:N38 -> 0 | Q38: =Tue!R33 -> 0
A39: BAR | B39: 75000 | C39: =I46 -> 0 | D39: =C39-B39 -> -75000 | L39: =Wed!O15 -> 0 | M39: =Wed!O20 -> 0 | O39: =SUM(M37:M39)-N37:N39 -> 0 | Q39: =Wed!R33 -> 0
A40: RETAIL | B40: 0 | C40: =H12 -> 0 | D40: =C40-B40 -> 0 | L40: =Thu!O15 -> 0 | M40: =Thu!O20 -> 0 | O40: =SUM(M37:M40)-N37:N40 -> 0 | Q40: =Thu!R33 -> 0
A41: WAGES | B41: 32000 | D41: =C41-B41 -> -32000 | L41: =Fri!O15 -> 0 | M41: =Fri!O20 -> 0 | O41: =SUM(M37:M41)-N37:N41 -> 0 | Q41: =Fri!R33 -> 0
A42: SECURITY | B42: 3000 | D42: =C42-B42 -> -3000 | L42: =Sat!O15 -> 0 | M42: =Sat!O20 -> 0 | O42: =SUM(M37:M42)-N37:N42 -> 0 | Q42: =Sat!R33 -> 0
L43: =Sun!O15 -> 0 | M43: =Sun!O20 -> 0 | O43: =SUM(M37:M43)-N37:N43 -> 0 | Q43: =Sun!R33 -> 0
L44: =SUM(L37:L43) -> 0 | M44: =SUM(M37:M43) -> 0 | P44: TOTAL | Q44: =SUM(Q37:Q43) -> 0
B45: MON | C45: TUE | D45: WED | E45: THUR | F45: FRI | G45: SAT | H45: SUN | I45: TOTAL | L45: AGENT FEE
A46: BARS | B46: =C5+D5+E5+F5 -> 0 | C46: =C6+D6+E6+F6 -> 0 | D46: =C7+D7+E7+F7 -> 0 | E46: =C8+D8+E8+F8 -> 0 | F46: =C9+D9+E9+F9 -> 0 | G46: =C10+D10+E10+F10 -> 0 | H46: =C11+D11+E11+F11 -> 0 | I46: =SUM(B46:H46) -> 0 | L46: SETTLE H.O | O46: TAB CHECK
A47: OVER/UNDER | B47: =Mon!K8+Mon!K15+Mon!K22+Mon!K28+Mon!K36+Mon!K42+Mon!K50+Mon!K57 -> 0 | C47: =Tue!K8+Tue!K15+Tue!K28+Tue!K42+Tue!K50+Tue!K22+Tue!K36+Tue!K57 -> 0 | D47: =Wed!K8+Wed!K15+Wed!K28+Wed!K42+Wed!K50+Wed!K22+Wed!K36+Wed!K57 -> 0 | E47: =Thu!K8+Thu!K15+Thu!K28+Thu!K42+Thu!K50+Thu!K22+Thu!K36+Thu!K57 -> 0 | F47: =Fri!K8+Fri!K15+Fri!K28+Fri!K42+Fri!K50+Fri!K22+Fri!K36+Fri!K57 -> 0 | G47: =Sat!K8+Sat!K15+Sat!K28+Sat!K42+Sat!K50+Sat!K22+Sat!K36+Sat!K57 -> 0 | H47: =Sun!K8+Sun!K15+Sun!K28+Sun!K42+Sun!K50+Sun!K22+Sun!K36+Sun!K57 -> 0 | I47: =SUM(B47:H47) -> 0 | L47: TOTAL | M47: =SUM(M45:M46) -> 0 | O47: =M44-M47 -> 0
A48: TYRO FEE | B48: =Mon!D8+Mon!D15+Mon!D28+Mon!D42+Mon!D50+Mon!D22+Mon!D36+Mon!D57 -> 0 | C48: =Tue!D8+Tue!D15+Tue!D28+Tue!D42+Tue!D50+Tue!D22+Tue!D36+Tue!D57 -> 0 | D48: =Wed!D8+Wed!D15+Wed!D28+Wed!D42+Wed!D50+Wed!D22+Wed!D36+Wed!D57 -> 0 | E48: =Thu!D8+Thu!D15+Thu!D28+Thu!D42+Thu!D50+Thu!D22+Thu!D36+Thu!D57 -> 0 | F48: =Fri!D8+Fri!D15+Fri!D28+Fri!D42+Fri!D50+Fri!D22+Fri!D36+Fri!D57 -> 0 | G48: =Sat!D8+Sat!D15+Sat!D28+Sat!D42+Sat!D50+Sat!D22+Sat!D36+Sat!D57 -> 0 | H48: =Sun!D8+Sun!D15+Sun!D28+Sun!D42+Sun!D50+Sun!D22+Sun!D36+Sun!D57 -> 0 | I48: =SUM(B48:H48) -> 0
A49: FOOD | B49: =Mon!R9 -> 0 | C49: =Tue!R9 -> 0 | D49: =Wed!R9 -> 0 | E49: =Thu!R9 -> 0 | F49: =Fri!R9 -> 0 | G49: =Sat!R9 -> 0 | H49: =Sun!R9 -> 0 | I49: =SUM(B49:H49) -> 0
A50: ACCOUNTS | B50: =Mon!L8+Mon!L15+Mon!L28+Mon!L42+Mon!L50+Mon!L22+Mon!L36+Mon!L57 -> 0 | C50: =Tue!L8+Tue!L15+Tue!L28+Tue!L42+Tue!L50+Tue!L22+Tue!L36+Tue!L57 -> 0 | D50: =Wed!L8+Wed!L15+Wed!L28+Wed!L42+Wed!L50+Wed!L22+Wed!L36+Wed!L57 -> 0 | E50: =Thu!L8+Thu!L15+Thu!L28+Thu!L42+Thu!L50+Thu!L22+Thu!L36+Thu!L57 -> 0 | F50: =Fri!L8+Fri!L15+Fri!L28+Fri!L42+Fri!L50+Fri!L22+Fri!L36+Fri!L57 -> 0 | G50: =Sat!L8+Sat!L15+Sat!L28+Sat!L42+Sat!L50+Sat!L22+Sat!L36+Sat!L57 -> 0 | H50: =Sun!L8+Sun!L15+Sun!L28+Sun!L42+Sun!L50+Sun!L22+Sun!L36+Sun!L57 -> 0 | I50: =SUM(B50:H50) -> 0
A51: TIPS | B51: =Mon!E57+Mon!E50+Mon!E42+Mon!E36+Mon!E28+Mon!E22+Mon!E15+Mon!E8 -> 0 | C51: =Tue!E8+Tue!E15+Tue!E22+Tue!E28+Tue!E36+Tue!E42+Tue!E50+Tue!E57 -> 0 | D51: =Wed!E57+Wed!E50+Wed!E42+Wed!E36+Wed!E28+Wed!E22+Wed!E15+Wed!E8 -> 0 | E51: =Thu!E57+Thu!E50+Thu!E42+Thu!E36+Thu!E28+Thu!E22+Thu!E15+Thu!E8 -> 0 | F51: =Fri!E57+Fri!E50+Fri!E42+Fri!E36+Fri!E28+Fri!E22+Fri!E15+Fri!E8 -> 0 | G51: =Sat!E57+Sat!E50+Sat!E42+Sat!E36+Sat!E28+Sat!E22+Sat!E15+Sat!E8 -> 0 | H51: =Sun!E57+Sun!E50+Sun!E42+Sun!E36+Sun!E28+Sun!E22+Sun!E15+Sun!E8 -> 0 | I51: =SUM(B51:H51) -> 0 | L51: FOOD | M51: LUNCH | N51: DINNER | O51: TOTAL
L52: MON | M52: ='Mon diary'!B45 -> 0 | N52: ='Mon diary'!D45 -> 0 | O52: =SUM(M52:N52) -> 0
I53: BANKING FIGURES | L53: TUE | M53: ='Tue diary'!B45 -> 0 | N53: ='Tue diary'!D45 -> 0 | O53: =SUM(M53:N53) -> 0
I54: EFTPOS/ATM | J54: =T31 -> 0 | L54: WED | M54: ='Wed diary'!B45 -> 0 | N54: ='Wed diary'!D45 -> 0 | O54: =SUM(M54:N54) -> 0
I55: TAB | J55: =M46 -> 0 | L55: THUR | M55: ='Thu diary'!B45 -> 0 | N55: ='Thu diary'!D45 -> 0 | O55: =SUM(M55:N55) -> 0
I56: TRADE (MO-TH) | J56: =O8 -> 0 | L56: FRI | M56: ='Fri diary'!B45 -> 0 | N56: ='Fri diary'!D45 -> 0 | O56: =SUM(M56:N56) -> 0
I57: TRADE (FR-SU) | J57: =O11 -> 0 | L57: SAT | M57: ='Sat diary'!B45 -> 0 | N57: ='Sat diary'!D45 -> 0 | O57: =SUM(M57:N57) -> 0
I58: TAB (ATM) | J58: =Q44 -> 0 | L58: SUN | M58: ='Sun diary'!B45 -> 0 | N58: ='Sun diary'!D45 -> 0 | O58: =SUM(M58:N58) -> 0
L59: TOTAL | M59: =SUM(M52:M58) -> 0 | N59: =SUM(N52:N58) -> 0 | O59: =SUM(O52:O58) -> 0

Sheet Safe Count
A1: REPUBLIC SAFE COUNT
A2: DAY | B2: Monday | C2: Monday
A3: DATE | B3: 46041
A4: TIME | B4: Rollover
A5: CRT FLOAT | B5: 97500 | C5: 97500 | D5: 87500 | E5: 87500 | F5: 87500 | G5: 87500 | H5: 87500 | I5: 87500 | J5: 97500 | K5: 97500 | L5: 97500 | M5: 97500 | N5: 97500 | O5: 97500 | P5: 97500 | Q5: 97500 | R5: 97500 | S5: 97500 | T5: 97500 | U5: 97500 | V5: 97500 | W5: 97500 | X5: 97500 | Y5: 97500 | Z5: 97500 | AA5: 97500 | AB5: 97500 | AC5: 97500 | AD5: 97500 | AE5: 97500 | AF5: 97500 | AG5: 97500 | AH5: 97500 | AI5: 97500 | AJ5: 97500 | AK5: 97500 | AL5: 97500 | AM5: 97500 | AN5: 97500 | AO5: 97500 | AP5: 97500 | AQ5: 97500 | AR5: 97500 | AS5: 97500 | AT5: 97500 | AU5: 97500 | AV5: 97500 | AW5: 97500 | AX5: 97500 | AY5: 97500 | AZ5: 97500 | BA5: 97500 | BB5: 97500 | BC5: 97500 | BD5: 97500 | BE5: 97500 | BF5: 97500 | BG5: 97500 | BH5: 97500 | BI5: 97500 | BJ5: 97500 | BK5: 97500 | BL5: 97500 | BM5: 97500
A7: ATM FLOAT | B7: 41000 | C7: 41000 | D7: 41000 | E7: 41000 | F7: 41000 | G7: 41000 | H7: 41000 | I7: 41000 | J7: 41000 | K7: 41000 | L7: 41000 | M7: 41000 | N7: 41000 | O7: 41000 | P7: 41000 | Q7: 41000 | R7: 41000 | S7: 41000 | T7: 41000 | U7: 41000 | V7: 41000 | W7: 41000 | X7: 41000 | Y7: 41000 | Z7: 41000 | AA7: 41000 | AB7: 41000 | AC7: 41000 | AD7: 41000 | AE7: 41000 | AF7: 41000 | AG7: 41000 | AH7: 41000 | AI7: 41000 | AJ7: 41000 | AK7: 41000 | AL7: 41000 | AM7: 41000 | AN7: 41000 | AO7: 41000 | AP7: 41000 | AQ7: 41000 | AR7: 41000 | AS7: 41000 | AT7: 41000 | AU7: 41000 | AV7: 41000 | AW7: 41000 | AX7: 41000 | AY7: 41000 | AZ7: 41000 | BA7: 41000 | BB7: 41000 | BC7: 41000 | BD7: 41000 | BE7: 41000 | BF7: 41000 | BG7: 41000 | BH7: 41000 | BI7: 41000 | BJ7: 41000 | BK7: 41000 | BL7: 41000 | BM7: 41000
A8: BAR TILL FLOATS | B8: 2000 | C8: 2000 | D8: 2000 | E8: 2000 | F8: 2000 | G8: 2000 | H8: 2000 | I8: 2000 | J8: 2000 | K8: 2000 | L8: 2000 | M8: 2000 | N8: 2000 | O8: 2000 | P8: 2000 | Q8: 2000 | R8: 2000 | S8: 2000 | T8: 2000 | U8: 2000 | V8: 2000 | W8: 2000 | X8: 2000 | Y8: 2000 | Z8: 2000 | AA8: 2000 | AB8: 2000 | AC8: 2000 | AD8: 2000 | AE8: 2000 | AF8: 2000 | AG8: 2000 | AH8: 2000 | AI8: 2000 | AJ8: 2000 | AK8: 2000 | AL8: 2000 | AM8: 2000 | AN8: 2000 | AO8: 2000 | AP8: 2000 | AQ8: 2000 | AR8: 2000 | AS8: 2000 | AT8: 2000 | AU8: 2000 | AV8: 2000 | AW8: 2000 | AX8: 2000 | AY8: 2000 | AZ8: 2000 | BA8: 2000 | BB8: 2000 | BC8: 2000 | BD8: 2000 | BE8: 2000 | BF8: 2000 | BG8: 2000 | BH8: 2000 | BI8: 2000 | BJ8: 2000 | BK8: 2000 | BL8: 2000 | BM8: 2000
A9: POKIE TILL FLOAT | B9: 1000 | C9: 1000 | D9: 1000 | E9: 1000 | F9: 1000 | G9: 1000 | H9: 1000 | I9: 1000 | J9: 1000 | K9: 1000 | L9: 1000 | M9: 1000 | N9: 1000 | O9: 1000 | P9: 1000 | Q9: 1000 | R9: 1000 | S9: 1000 | T9: 1000 | U9: 1000 | V9: 1000 | W9: 1000 | X9: 1000 | Y9: 1000 | Z9: 1000 | AA9: 1000 | AB9: 1000 | AC9: 1000 | AD9: 1000 | AE9: 1000 | AF9: 1000 | AG9: 1000 | AH9: 1000 | AI9: 1000 | AJ9: 1000 | AK9: 1000 | AL9: 1000 | AM9: 1000 | AN9: 1000 | AO9: 1000 | AP9: 1000 | AQ9: 1000 | AR9: 1000 | AS9: 1000 | AT9: 1000 | AU9: 1000 | AV9: 1000 | AW9: 1000 | AX9: 1000 | AY9: 1000 | AZ9: 1000 | BA9: 1000 | BB9: 1000 | BC9: 1000 | BD9: 1000 | BE9: 1000 | BF9: 1000 | BG9: 1000 | BH9: 1000 | BI9: 1000 | BJ9: 1000 | BK9: 1000 | BL9: 1000 | BM9: 1000
A10: TAB TILL FLOAT | B10: 1000 | C10: 1000 | D10: 1000 | E10: 1000 | F10: 1000 | G10: 1000 | H10: 1000 | I10: 1000 | J10: 1000 | K10: 1000 | L10: 1000 | M10: 1000 | N10: 1000 | O10: 1000 | P10: 1000 | Q10: 1000 | R10: 1000 | S10: 1000 | T10: 1000 | U10: 1000 | V10: 1000 | W10: 1000 | X10: 1000 | Y10: 1000 | Z10: 1000 | AA10: 1000 | AB10: 1000 | AC10: 1000 | AD10: 1000 | AE10: 1000 | AF10: 1000 | AG10: 1000 | AH10: 1000 | AI10: 1000 | AJ10: 1000 | AK10: 1000 | AL10: 1000 | AM10: 1000 | AN10: 1000 | AO10: 1000 | AP10: 1000 | AQ10: 1000 | AR10: 1000 | AS10: 1000 | AT10: 1000 | AU10: 1000 | AV10: 1000 | AW10: 1000 | AX10: 1000 | AY10: 1000 | AZ10: 1000 | BA10: 1000 | BB10: 1000 | BC10: 1000 | BD10: 1000 | BE10: 1000 | BF10: 1000 | BG10: 1000 | BH10: 1000 | BI10: 1000 | BJ10: 1000 | BK10: 1000 | BL10: 1000 | BM10: 1000
A12: TOTAL FLOATS | B12: =SUM(B5:B11) -> 142500 | C12: =SUM(C5:C11) -> 142500 | D12: =SUM(D5:D11) -> 132500 | E12: =SUM(E5:E11) -> 132500 | F12: =SUM(F5:F11) -> 132500 | G12: =SUM(G5:G11) -> 132500 | H12: =SUM(H5:H11) -> 132500 | I12: =SUM(I5:I11) -> 132500 | ... BM12: =SUM(BM5:BM11) -> 142500
A14: 100 | B14: 7400
A15: 50 | B15: 7000
A16: 20 | B16: 680
A17: 10 | B17: 490
A18: 5 | B18: 150
A19: LOOSE NOTES
A21: 2 | B21: 124
A22: 1 | B22: 81
A23: 50c | B23: 44
A24: 20c | B24: 7
A25: 10c | B25: 24
A26: 5c
A27: LOOSE COINS
A29: AMEX
A30: PETTY CASH
A31: PROMOS
A32: CHITS
A34: CHEQUES
A35: POKIE INCREASE
A36: KENO INCREASE
A37: TAB INCREASE
A38: GAMING CHEQUES
A40: HEAD OFFICE
... A42: CHANGE
A43: JT | B43: 1500
A44: TAKINGS NEGATIVE
A45: TAB NEGATIVE
A46: ATM/TAB Deposit
A48: TOTAL | B48: =SUM(B12:B47) -> 160000 | C48: =SUM(C12:C47) -> 142500 | D48: =SUM(D12:D47) -> 132500 | E48: =SUM(E12:E47) -> 132500 | F48: =SUM(F12:F47) -> 132500 | G48: =SUM(G12:G47) -> 132500 | H48: =SUM(H12:H47) -> 132500 | I48: =SUM(I12:I47) -> 132500 | ... BM48: =SUM(BM12:BM47) -> 142500
A49: SAFE FLOAT | B49: 160000 | C49: =B49 -> 160000 | D49: =C49 -> 160000 | E49: =D49 -> 160000 | F49: =E49 -> 160000 | G49: =F49 -> 160000 | H49: =G49 -> 160000 | I49: =H49 -> 160000 | J49: =I49 -> 160000 | ... AN49: =AM49 -> 160000 | AO49: 190000 | AP49: =AO49 -> 190000 | AQ49: =AP49 -> 190000 | AR49: =AQ49 -> 190000 | AS49: =AR49 -> 190000 | AT49: =AS49 -> 190000 | AU49: =AT49 -> 190000 | AV49: =AU49 -> 190000 | AW49: =AV49 -> 190000 | ... BM49: =BL49 -> 190000
A50: VARIANCE | B50: =B48-B49 -> 0 | C50: =C48-C49 -> -17500 | D50: =D48-D49 -> -27500 | E50: =E48-E49 -> -27500 | F50: =F48-F49 -> -27500 | G50: =G48-G49 -> -27500 | H50: =H48-H49 -> -27500 | I50: =I48-I49 -> -27500 | ... BM50: =BM48-BM49 -> -47500
A51: SIGNED | B51: AM
C57: c | X57: c | AL57: c | AZ57: c

Sheet EOW Report
A1: The Republic
A2: Week Ending
A3: =Takings!P2 -> 46061
B5: Actual | C5: Targets | D5: Actual % | E5: Target %
A6: Total Labour | D6: =SUM(B6/B21*1.12) -> #DIV/0!
A7: Annual Leave
A8: Other Leave (Sick, Maternity, Workers Comp)
A11: Revenue Summary | B11: Week | C11: Targets | E11: ME & U | G11: % of Sales
A12: Gaming Turnover | B12: =SUM(Takings!B31) -> 0 | E12: Food Sales | F12: 0 | G12: =SUM(F12/B15) -> #DIV/0!
A13: Gaming Net | B13: =SUM(Takings!H31) -> 0 | E13: Bev Sales | F13: 0 | G13: =SUM(F13/B14) -> #DIV/0!
A14: Beverage | B14: =SUM(Takings!C12:F12) -> 0 | E14: Other | F14: 0
A15: Food | B15: =SUM(Takings!G12) -> 0 | E15: Total Sales | F15: =SUM(F12:F14) -> 0
A16: Bottle Shop/Retail | B16: 0
A17: Accommodation | B17: 0 | E17: Orders | F17: 0
A18: TAB Turnover | B18: =Takings!L44 -> 0 | E18: Customers | F18: 0
A19: TAB Commission | B19: =Takings!M45 -> 0 | E19: ATV | F19: 0
A20: Sundries | B20: =SUM(Takings!J12)-B19 -> 0
A21: Total Venue Revenue | B21: =B13+B14+B15+B16+B19+B20 -> 0 | C21: =SUM(C13:C20) -> 0
A23: Comments
A25: Labour
A33: Gaming
A41: Bars
A49: Food
A57: Bottleshop
A65: Accommodation
A73: Team Health
A81: The Week Ahead

Sheet Petty Cash
A1: Petty Cash | C1: =Takings!F1 -> Republic Hotel | E1: Week End: | F1: =Takings!P2 -> 46061
A3: DATE | B3: SUPPLIER | C3: PURCHSED FOR | D3: APPROVED BY | E3: TOTAL | F3: NET | G3: GST
F4: =E4-G4 -> 0 | G4: 0
F5: =E5-G5 -> 0 | G5: 0
F6: =E6-G6 -> 0 | G6: =E6/11 -> 0
F7: =E7-G7 -> 0 | G7: 0
F8: =E8-G8 -> 0 | G8: 0
F9: =E9-G9 -> 0 | G9: 0
F10: =E10-G10 -> 0 | G10: 0
F11: =E11-G11 -> 0 | G11: 0
F12: =E12-G12 -> 0 | G12: =E12/11 -> 0
F13: =E13-G13 -> 0 | G13: 0
F14: =E14-G14 -> 0 | G14: 0
F15: =E15-G15 -> 0 | G15: =E15/11 -> 0
F16: =E16-G16 -> 0 | G16: =E16/11 -> 0
F17: =E17-G17 -> 0 | G17: =E17/11 -> 0
F18: =E18-G18 -> 0 | G18: =E18/11 -> 0
F19: =E19-G19 -> 0 | G19: =E19/11 -> 0
F20: =E20-G20 -> 0 | G20: =E20/11 -> 0
F21: =E21-G21 -> 0 | G21: =E21/11 -> 0
F22: =E22-G22 -> 0 | G22: =E22/11 -> 0
F23: =E23-G23 -> 0 | G23: =E23/11 -> 0
F24: =E24-G24 -> 0 | G24: =E24/11 -> 0
F25: =E25-G25 -> 0 | G25: =E25/11 -> 0
F26: =E26-G26 -> 0 | G26: =E26/11 -> 0
... F39: =E39-G39 -> 0 | G39: =E39/11 -> 0
D40: TOTAL | E40: =SUM(E4:E39) -> 0 | F40: =SUM(F4:F39) -> 0 | G40: =SUM(G4:G39) -> 0

Sheet WAGES
A1: Location | B1: Revenue | C1: Wage Cost | D1: Wage Percentage
A2: Bar | B2: =SUM('EOW Report'!B14) -> 0 | D2: =B2/$C$2 -> #DIV/0!
A3: Kitchen | B3: ='EOW Report'!B15 -> 0 | D3: =B3/$C$2 -> #DIV/0!
A4: Gaming | B4: ='EOW Report'!B13 -> 0 | D4: =B4/$C$2 -> #DIV/0!
A5: Management
A6: Other | B6: ='EOW Report'!B19+'EOW Report'!B20 -> 0
A7: Total Wages | B7: =SUM(B2:B5) -> 0 | C7: =SUM(C2:C5) -> 0
A9: Revenue will automatically populate. Enter in the wages from each department from the payroll report. The wgaes percentage will auto calculate

Sheet Banking EOW
A1: Trade | D1: TAB | G1: Keno | J1: Pokie Cheques | M1: Misc | P1: Misc
A2: Cash | D2: Cash | G2: Cash | J2: Cash | M2: Cash | P2: Cash
A3: 100 | D3: 100 | G3: 100 | J3: 100 | M3: 100 | P3: 100
A4: 50 | D4: 50 | G4: 50 | J4: 50 | M4: 50 | P4: 50
A5: 20 | D5: 20 | G5: 20 | J5: 20 | M5: 20 | P5: 20
A6: 10 | D6: 10 | G6: 10 | J6: 10 | M6: 10 | P6: 10
A7: 5 | D7: 5 | G7: 5 | J7: 5 | M7: 5 | P7: 5
A8: Total Notes | B8: =SUM(B3:B7) -> 0 | D8: Total Notes | E8: =SUM(E3:E7) -> 0 | G8: Total Notes | H8: =SUM(H3:H7) -> 0 | J8: Total Notes | K8: =K3+K4+K5+K6+K7 -> 0 | M8: Total Notes | N8: =SUM(N3:N7) -> 0 | P8: Total Notes | Q8: =SUM(Q3:Q7) -> 0
A9: Coin | D9: Coin | G9: Coin | J9: Coin | M9: Coin | P9: Coin
A10: Cash Total | B10: =SUM(B8:B9) -> 0 | D10: Cash Total | E10: =SUM(E8:E9) -> 0 | G10: Cash Total | H10: =SUM(H8:H9) -> 0 | J10: Cash Total | K10: =SUM(K8:K9) -> 0 | M10: Cash Total | N10: =SUM(N8:N9) -> 0 | P10: Cash Total | Q10: =SUM(Q8:Q9) -> 0
A12: Cheques | D12: Cheques | G12: Cheques | J12: Cheques | M12: Cheques | P12: Cheques
A24: Cheque Total | B24: =SUM(A13:B23) -> 0 | D24: Cheque Total | E24: =SUM(D13:E23) -> 0 | G24: Cheque Total | H24: =SUM(G13:H23) -> 0 | J24: Cheque Total | K24: =SUM(J13:K23) -> 0 | M24: Cheque Total | N24: =SUM(M13:N23) -> 0 | P24: Cheque Total | Q24: =SUM(P13:Q23) -> 0
A26: Banking Total | B26: =B24+B10 -> 0 | D26: Banking Total | E26: =E24+E10 -> 0 | G26: Banking Total | H26: =H24+H10 -> 0 | J26: Banking Total | K26: =K24+K10 -> 0 | M26: Banking Total | N26: =N24+N10 -> 0 | P26: Banking Total | Q26: =Q24+Q10 -> 0
A28: Variance +/- | B28: =B26-Takings!O12 -> 0 | D28: Variance +/- | E28: =E26-Takings!M46 -> 0 | G28: Variance +/- | H28: =E15 -> 0 | J28: Variance +/- | K28: =K26-K32 -> 0
A29: EDB Ref #: | D29: EDB Ref #: | G29: EDB Ref #: | J29: EDB Ref #: | M29: EDB Ref #: | P29: EDB Ref #:
A32: ATM/EFT | B32: =Takings!T31 -> 0 | J32: Gaming CHQ
A33: EDB Ref #:
A35: Grand Total
A36: Cash | B36: =B10+E10+H10+K10+N10+Q10 -> 0
A37: Cheques | B37: =B24+E24+H24+K24+N24+Q24+B32 -> 0
A38: =SUM(B36:B37) -> 0
A39: No. Of Bags:
